{
    "VERSE": "67:19",
    "ARABIC": "\u0623\u064e\u0648\u064e\u0644\u064e\u0645\u0652 \u064a\u064e\u0631\u064e\u0648\u0652\u0627\u06df \u0625\u0650\u0644\u064e\u0649 \u0671\u0644\u0637\u0651\u064e\u064a\u0652\u0631\u0650 \u0641\u064e\u0648\u0652\u0642\u064e\u0647\u064f\u0645\u0652 \u0635\u064e\u0670\u0653\u0641\u0651\u064e\u0670\u062a\u064d \u0648\u064e\u064a\u064e\u0642\u0652\u0628\u0650\u0636\u0652\u0646\u064e \u0645\u064e\u0627 \u064a\u064f\u0645\u0652\u0633\u0650\u0643\u064f\u0647\u064f\u0646\u0651\u064e \u0625\u0650\u0644\u0651\u064e\u0627 \u0671\u0644\u0631\u0651\u064e\u062d\u0652\u0645\u064e\u0670\u0646\u064f \u0625\u0650\u0646\u0651\u064e\u0647\u064f\u06e5 \u0628\u0650\u0643\u064f\u0644\u0651\u0650 \u0634\u064e\u0649\u0652\u0621\u064d\u06ed \u0628\u064e\u0635\u0650\u064a\u0631\u064c",
    "ENGLISH": {
        "TRANSLATION_0": "Have they not looked at the birds above them, with wings outspread and folded back? Nothing holds them up but the All-Merciful. He sees all things.",
        "TRANSLATION_1": "Do they not see the birds above them flying wings spread out or folded? Nothing holds them aloft but God. All things are within His purview.\n",
        "TRANSLATION_2": "Have they not seen birds above them spreading and closing their wings, with none holding them except the Merciful One? He oversees everything.\n",
        "TRANSLATION_3": "Did they not see the birds above them, stretching out, and flapping their wings. No one keeps them up in the sky except the Beneficent God. He certainly watches over all things.\n",
        "TRANSLATION_4": "And did they not see the birds above them, spreading and closing their wings? None except the Most Gracious holds them up; indeed He sees all things.\n",
        "TRANSLATION_5": "Do they not see the birds above them, spreading out their wings and folding them in None upholds them except the Most Gracious. Verily, He is the All-Seer of everything.\n",
        "TRANSLATION_6": "Have they not seen the birds above them expanding (their wings) and contracting (them)? What is it that withholds them save the Beneficent Allah? Surely He sees everything.\n",
        "TRANSLATION_7": "Have they not regarded the birds above them spreading their wings, and closing them? Naught holds them but the All-merciful. Surely He sees everything.\n",
        "TRANSLATION_8": "Have they not seen the birds above them spreading out their wings and closing them? Naught upholdeth them save the Beneficent. Lo! He is Seer of all things.\n",
        "TRANSLATION_9": "Do they not see the birds above them spreading and closing their wings? None save the Merciful sustains them. Surely, He observes all things.\n",
        "TRANSLATION_10": "Behold they not the birds above them, outstretching their wings and they also withdraw them? Naught holdeth them except the Compassionate. Verily He is of everything Beholder.\n",
        "TRANSLATION_11": "Have they not regarded the birds above them spreading and closing their wings? No one sustains them except the All-beneficent. Indeed, He watches all things.\n",
        "TRANSLATION_12": "Do they not observe the birds above them, spreading their wings and folding them in? None can uphold them except (Allah) Most Gracious: Truly (Allah) Most Gracious: Truly it is He that watches over all things.\n",
        "TRANSLATION_13": "Do they not see the birds above them, spreading out their wings and folding them in? None upholds them except the Most Beneficent (Allah). Verily, He is the All-Seer of everything.\n",
        "TRANSLATION_14": "Do they not observe the birds above them, spreading their wings and folding them? None, except the Merciful holds them. Surely, He sees all things.\n",
        "TRANSLATION_15": "Have they not seen the birds above them, spreading their wings, and folding them? None holds them except the Compassionate. He is Perceiver of everything.\n",
        "TRANSLATION_16": "Do they not see the birds above them with wings outspread and [sometimes] folded in? None holds them [aloft] except the Most Merciful. Indeed He is, of all things, Seeing.\n",
        "TRANSLATION_17": "[67:19] Or have they not seen the birds above them, in the air, spreading their wings and closing?, their wings after spreading them? (in other words [read wa-yaqbidna] as wa-q\u0101bid\u0101tin [similar to s\u0101ff\u0101tin, \u2018spreading\u2019]). Nothing sustains them, from falling, either when they are spreading them or closing them, except the Compassionate One, by His power. Indeed He is Seer of all things. The meaning is: have they not inferred from the fact that the birds [are able to] remain in the air that We have the power to do with them what has been mentioned above as well as [inflicting upon them] other kinds of chastisement?\n",
        "TRANSLATION_18": "(Have they) i.e. the disbelievers of Mecca (not seen the birds above them) above their heads (spreading out their wings and closing them? Naught upholdeth them) after their spreading out (save the Beneficent. Lo! He is Seer of all things) whether it is spreading out or closing.\n"
    },
    "CROSS_REFERENCE": {
        "QURAN": [
            "67:19",
            "54:52",
            "36:15",
            "26:5",
            "13:8",
            "11:57",
            "36:12",
            "46:33",
            "54:49",
            "40:20"
        ],
        "BIBLE": [
            "prophets:ii%20samuel:22:11",
            "writings:lamentations:1:10",
            "prophets:isaiah:42:20",
            "torah:exodus:19:4",
            "writings:i%20chronicles:29:17",
            "torah:deuteronomy:10:21",
            "writings:job:28:21",
            "torah:genesis:22:12",
            "torah:genesis:16:13",
            "prophets:isaiah:33:23"
        ]
    },
    "FEATURES": [
        "NO",
        "inhibit.v.04",
        "IOUS",
        "ADIN",
        "means.n.01",
        "AIN",
        " SA",
        "aim.n.02",
        "ACI",
        "DI",
        "have.v.12",
        " REG",
        "LDET",
        "inform.v.01",
        "G ",
        "EFI",
        "PAN",
        "spiritual_being.n.01",
        "verify.v.01",
        "lodge.v.04",
        "forget.v.01",
        "SEES",
        "request.v.01",
        "most.r.01",
        "RSE",
        "state.v.01",
        "NT ",
        "LOO",
        "DRAW",
        "disable.v.01",
        " SE",
        "OD ",
        "leave.v.01",
        "close.v.09",
        " SK",
        "look.v.09",
        "ED ",
        "one.n.01",
        "BEH",
        "diffuse.v.01",
        "do.v.13",
        "agree.v.01",
        " D",
        "exist.v.01",
        "OLDE",
        "scat.v.01",
        "UGH",
        "stretch.v.08",
        "female.n.02",
        "EHOL",
        "disengage.v.01",
        " ARE",
        "consume.v.02",
        "player.n.01",
        "LOOK",
        "curiosity.n.01",
        "CIO",
        "copulate.v.01",
        " GRA",
        "keep.v.09",
        "OFT",
        "reading.n.03",
        "change_surface.v.01",
        "VIE",
        "DEE",
        "RETC",
        "NGS ",
        "TRAC",
        "WITH",
        "atmosphere.n.05",
        "RVIE",
        "bird.n.01",
        "HIN",
        "aloft.r.01",
        "CTIN",
        " ALO",
        "abstraction.n.01",
        "EAD ",
        "retire.v.02",
        "lie_down.v.01",
        "flap.v.02",
        "NOTHING",
        "PS ",
        "SO",
        "FOLD",
        " ONE",
        "N ",
        "AUG",
        "leave.v.08",
        "wing.n.01",
        "integrate.v.01",
        "remove.v.01",
        "fly.v.07",
        "make.v.01",
        "ONA",
        "integer.n.01",
        "OMP",
        "ST ",
        "UTS",
        "chordate.n.01",
        "SPREAD_OUT",
        "lie.v.01",
        "D_OU",
        "determine.v.08",
        "explain.v.01",
        "PING",
        "L-B",
        "increase.v.02",
        "ACTI",
        "location.n.01",
        "EI",
        "fender.n.01",
        "OUT",
        "transfer.v.02",
        "OD",
        " THI",
        "hit.v.01",
        "pronounce.v.01",
        "close.v.13",
        "-BE",
        "XP",
        "entity.n.01",
        "RELY",
        "sincerely.r.01",
        "refrain.v.01",
        "corrupt.v.04",
        "YTHI",
        "PI",
        "AV",
        "SOMETIMES",
        "platform.n.01",
        "do.v.08",
        "respect.v.02",
        "NAT",
        "none.n.02",
        "RCI",
        "tell.v.02",
        " GOD",
        "IO",
        "EER",
        "keep.v.15",
        "RVE",
        "TIME",
        "event.n.01",
        "trade.v.03",
        "change.v.01",
        "OB",
        " R",
        "outspread.s.01",
        "PU",
        "advance.v.01",
        "AD_",
        "relative_quantity.n.01",
        "PURVIEW",
        " LOO",
        "tense.v.04",
        "interest.n.01",
        "TSP",
        "SKY",
        "WIN",
        " OUT",
        "administer.v.01",
        "AD",
        "AS",
        "attract.v.02",
        "things.n.01",
        "decrease.v.01",
        "HE",
        "wing.n.04",
        "magnitude.n.01",
        "ELY ",
        "VIEW",
        "EN",
        "sky.n.01",
        "thing.n.12",
        "utterance.n.01",
        "oblige.v.02",
        "MERCIFUL",
        " SU",
        "state.n.02",
        " WIT",
        "aloft.r.04",
        "EES ",
        "identify.v.01",
        "adjourn.v.02",
        "SEER",
        "TIN",
        "US ",
        "LL",
        "travel.v.04",
        "OF",
        "AL",
        "see.v.11",
        "FICE",
        "intellectual.n.01",
        "include.v.01",
        "serve.v.09",
        "PURV",
        "witness.v.02",
        "SUR",
        "LAH ",
        "ATC",
        "make.v.02",
        "horizontal_surface.n.01",
        "ERT",
        "HOLDS",
        "ALL-SEER",
        "CENT",
        "RACI",
        "create.v.05",
        "-BEN",
        "obstruction.n.01",
        " HO",
        "reject.v.01",
        "DET",
        "RYTH",
        "stretch.v.06",
        "NEFI",
        "DIN",
        "body_part.n.01",
        "better.v.02",
        "FT",
        "consort.v.01",
        "truly.r.01",
        "SOM",
        "HOLD",
        "AN",
        "LOSI",
        " SAV",
        "matter.n.01",
        "PUR",
        "OM",
        "fly.v.12",
        "AU",
        "CHI",
        "COMP",
        "groom.v.03",
        "suffer.v.03",
        "verily.r.01",
        "RDED",
        " L",
        "TI",
        "auditory_communication.n.01",
        "aloft.r.03",
        "EXPA",
        " KE",
        "ONE ",
        "GR",
        " FOL",
        "LAP",
        "ONTR",
        "leader.n.01",
        "SIN",
        "-ME",
        "keep_open.v.01",
        "PP",
        "restrain.v.03",
        "rescue.v.01",
        " SUR",
        "move.v.02",
        "INS",
        "change_by_reversal.v.01",
        "think.v.01",
        "PA",
        " VER",
        "EVE",
        "EL",
        "DER ",
        "THH",
        "physical_entity.n.01",
        "have.v.09",
        "EE ",
        "TH",
        "WATC",
        " DO",
        "MER",
        "URVI",
        " PU",
        "NGS",
        "REGA",
        "postpone.v.01",
        "support.v.01",
        "FOLDED",
        "UPHOLDETH",
        "defend.v.01",
        "PAS",
        "K ",
        "expect.v.03",
        " VE",
        "see.v.15",
        "unit.n.04",
        "CTI",
        "OBS",
        "SI",
        "stretch.v.02",
        "URV",
        "DR",
        " SP",
        " FO",
        "see.v.10",
        "one.n.02",
        "defy.v.01",
        "SPRE",
        "IFU",
        "tighten.v.02",
        "AP",
        "URE",
        "ID ",
        "IM",
        "fly.v.01",
        "DER",
        "VES ",
        "ALSO",
        "hold.v.33",
        "continue.v.03",
        "stretch.v.07",
        "OT",
        "prosecute.v.03",
        "observe.v.08",
        "WINGS",
        "effect.v.01",
        "keep.v.03",
        "OO",
        "STAI",
        "be.v.03",
        "IL",
        "NAUGHT",
        "NAUG",
        "beat.v.04",
        "check.v.01",
        "LOFT",
        "be.v.01",
        "relate.v.05",
        "D_O",
        "proceed.v.04",
        "shuttlecock.n.01",
        "BENE",
        "METI",
        "BI",
        "SU",
        "in_truth.r.01",
        "cognitive_state.n.01",
        "relation.n.01",
        "EEIN",
        "MOS",
        "TAIN",
        "retire.v.01",
        "NDI",
        "thing.n.09",
        " IND",
        "OOK",
        "THIN",
        "AD_O",
        "CIF",
        "see.v.12",
        "IE",
        "ERS",
        "LDI",
        "RAC",
        "distinguish.v.01",
        "UR",
        " CON",
        "thing.n.11",
        "prolong.v.02",
        "seer.n.02",
        "indeed.r.01",
        "withhold.v.01",
        "athlete.n.01",
        "talk.v.02",
        "LOF",
        " EXP",
        "SEE",
        "hold.v.16",
        " N",
        "beat.v.08",
        "person.n.01",
        " B",
        "change_shape.v.01",
        "OST ",
        "TSTR",
        "devolve.v.03",
        "unit.n.03",
        "shrink.v.03",
        "confirm.v.01",
        "AN ",
        "INGS",
        "LSO",
        "EV",
        " TR",
        "FT ",
        " MOS",
        "DID",
        "symbol.n.02",
        "UTST",
        " OVE",
        "KEE",
        "situation.n.01",
        "ERIL",
        "LL-S",
        " OU",
        " SPR",
        "DE",
        "withdraw.v.01",
        "drink.v.02",
        "KY ",
        "L-BE",
        "contend.v.06",
        "S ",
        "expand.v.02",
        " CO",
        "BE",
        "_O",
        "OVE",
        "GS",
        "MET",
        "beneficent.s.02",
        "EW ",
        "create_from_raw_material.v.01",
        " EX",
        " BA",
        "interpret.v.01",
        "HA",
        "NON",
        "HOLDING",
        "ING ",
        "RCE",
        "unfold.v.04",
        "KEEPS",
        "about.r.07",
        "TRUL",
        "contract.v.01",
        "EXP",
        "L-ME",
        "travel.v.05",
        "-S",
        " CA",
        "CLOSING",
        "NEF",
        "flank.n.01",
        "declare.v.01",
        "wing.n.08",
        "prophet.n.01",
        "retreat.v.04",
        "do.v.11",
        "TRA",
        "stay.v.01",
        "FIC",
        "note.v.03",
        "creation.n.02",
        "device.n.01",
        "hold.v.10",
        " DI",
        "vertebrate.n.01",
        "show.v.04",
        "ETIM",
        "express.v.02",
        "carry_through.v.01",
        "SAVE",
        "component.n.03",
        "observe.v.04",
        "none.n.01",
        "protect.v.01",
        "seclude.v.01",
        "manage.v.02",
        "L-S",
        "act.v.01",
        "OUS ",
        "LOS",
        "UL",
        "NLY ",
        "OLD ",
        " EV",
        "hockey_player.n.01",
        "-SE",
        "belief.n.01",
        "EED ",
        "US",
        "RS",
        "RV",
        "watch.v.01",
        "position.v.01",
        "RILY",
        "ID",
        "TING",
        "score.v.01",
        "IRDS",
        "observe.v.09",
        "RE",
        " UP",
        "make.v.03",
        "travel.v.03",
        "prevail.v.02",
        "PREA",
        "get.v.01",
        "ME",
        "digit.n.01",
        "AINS",
        "horizon.n.02",
        "HT",
        "EAD",
        "UGHT",
        "ACK",
        "XPA",
        "FUL",
        " ] ",
        "spread.v.01",
        "SA",
        "INDE",
        "EXPANDING",
        "TH ",
        "annex.n.01",
        "THINGS",
        "KE",
        "SUSTAINS",
        "declare.v.04",
        "uphold.v.02",
        "CI",
        "attribute.n.02",
        "indefinite_quantity.n.01",
        "TE ",
        "ARE ",
        " OV",
        "VERILY",
        "WITHDRAW",
        "GOD",
        "hash_out.v.01",
        "EIV",
        "service.n.03",
        "representation.n.02",
        "REL",
        "badge.n.01",
        "promise.v.01",
        "concept.n.01",
        "imagine.v.01",
        "PERCEIVER",
        "have.v.07",
        "keep.v.20",
        "fuss.v.01",
        "WAT",
        "RD",
        "conclude.v.04",
        "YTH",
        "record.v.02",
        "LAPP",
        "compassionate.a.01",
        "travel.v.02",
        "hold.v.31",
        "CL",
        "STRE",
        " BE",
        "TAI",
        "RC",
        "ATCH",
        "cognition.n.01",
        "note.v.01",
        "ITHD",
        "APP",
        "VE",
        "ICEN",
        "NTRA",
        "NA",
        "EGA",
        "barricade.v.01",
        "IV",
        "OLD",
        "compress.v.02",
        "load.v.05",
        "keep.v.18",
        "close.v.17",
        "approach.v.01",
        "contain.v.05",
        "arrangement.n.02",
        "BIRDS",
        "MO",
        " NAU",
        "HES ",
        " U",
        "ALOFT",
        "BS",
        "YT",
        "OSIN",
        " NON",
        "ATE ",
        "extend.v.17",
        "LOOKED",
        "benignant.s.02",
        "EEPS",
        "PRE",
        "AI",
        "clarify.v.01",
        "insignia.n.01",
        "SERV",
        "content.n.05",
        "courteous.s.01",
        "take.v.35",
        "sports_equipment.n.01",
        "CEI",
        "LDER",
        " H",
        "NATE",
        "NS",
        "detect.v.01",
        "IN",
        "communicate.v.02",
        "organ.n.01",
        "ILY",
        " HA",
        "LL-B",
        "keep.v.12",
        "CLO",
        "GRA",
        "H ",
        "LDS",
        "fluid.n.02",
        "fly.v.10",
        "Y ",
        "handle.v.04",
        "pen_up.v.01",
        "change_state.v.01",
        "elapse.v.01",
        "have.v.01",
        "UT",
        "learn.v.02",
        " ]",
        "transfer.v.05",
        "WI",
        "regard.v.02",
        "failure.n.01",
        "IME",
        "CHIN",
        "SING",
        "spend.v.01",
        "store.v.02",
        "MES ",
        "ICE",
        "happening.n.01",
        "uphold.v.03",
        "SS",
        "EX",
        "ARE",
        "spy.v.03",
        "clock_time.n.01",
        "extend.v.09",
        "RU",
        "PH",
        "go_steady.v.01",
        "HO",
        "look.v.07",
        "THD",
        "NDEE",
        "information.n.02",
        "TC",
        "ERC",
        "hold.v.36",
        "keep.v.08",
        "spread.v.02",
        "AT",
        "XPAN",
        "EADI",
        "save.v.06",
        "join.v.02",
        "ITHH",
        "circulate.v.03",
        "ASSI",
        "flap.v.06",
        "accompany.v.02",
        "AINL",
        " ON",
        " G",
        "go_around.v.02",
        "OST",
        "stretch.v.04",
        "attend.v.02",
        "FLAP",
        " K",
        "OTHI",
        "behold.v.01",
        "ENT",
        "SP",
        "wing.n.06",
        "EFIC",
        "EA",
        "close.v.11",
        "ELY",
        "hold.v.28",
        "condense.v.07",
        "see.v.22",
        "end.v.03",
        "INLY",
        "fight.v.02",
        "LYIN",
        "AND",
        "have.v.02",
        "LO",
        "DED",
        "point.n.02",
        "narrow.v.01",
        "TCH",
        "elongate.v.01",
        "equal.v.01",
        "KED ",
        "sicken.v.02",
        "DO",
        "isolate.v.01",
        "LDE",
        "close.v.14",
        "hold.v.02",
        " NA",
        "act.n.02",
        "LSO ",
        "PE",
        "affirm.v.03",
        "definite_quantity.n.01",
        "EF",
        "worry.v.01",
        "hold.v.22",
        "GH",
        "see.v.23",
        "CEIV",
        "control.v.02",
        " SOM",
        "UG",
        "religious_ceremony.n.01",
        "BACK",
        "FL",
        "watch.v.02",
        "psychological_feature.n.01",
        "restrain.v.01",
        "THDR",
        "diviner.n.01",
        "O ",
        "BEN",
        "NDE",
        "experience.v.03",
        "save.v.05",
        "MOST",
        "YING",
        "effigy.n.01",
        "T ",
        "see.v.19",
        "LDIN",
        "NDIN",
        "front.v.01",
        "OUTSTRETCHING",
        "spread.v.07",
        "disown.v.02",
        "wing.n.03",
        "PHO",
        "NG ",
        "supply.v.01",
        "SEEING",
        "thing.n.10",
        "addition.n.01",
        "close.v.04",
        "_OU",
        "extent.n.02",
        "resist.v.02",
        "solid.n.01",
        "ACIO",
        "naught.n.02",
        "elaborate.v.01",
        "close.v.10",
        "act.v.02",
        "GAR",
        "KY",
        "WATCHES",
        "sleep_together.v.01",
        "property.n.02",
        "receive.v.01",
        "IS ",
        "datum.n.01",
        "MP",
        "GARD",
        "CO",
        "halt.v.01",
        "defend.v.03",
        "idea.n.01",
        "search.v.02",
        "count.v.08",
        "convey.v.03",
        "STA",
        " S",
        "formation.n.01",
        "take.v.08",
        "OMET",
        "CA",
        "dither.v.02",
        "PPI",
        "NOT ",
        "EH",
        "psychological_state.n.01",
        "SKY ",
        "have.v.10",
        "ITH",
        "oversee.v.01",
        "leave_office.v.01",
        "contract.v.04",
        "barrier.n.01",
        " NO",
        "IC",
        "IS",
        "put.v.01",
        "EGAR",
        "EEI",
        "RYT",
        "[",
        "rightfully.r.01",
        " BIR",
        "cook.v.02",
        "sign.v.04",
        "SIO",
        "wings.n.01",
        "IF",
        "suffer.v.06",
        "MPAS",
        "basic_cognitive_process.n.01",
        "bird.n.02",
        "FLA",
        "RT",
        "NE ",
        "EG",
        "FO",
        "badminton_equipment.n.01",
        "EW",
        "roll.v.11",
        "nourish.v.01",
        "boo.n.01",
        "NS ",
        "NOTH",
        "CONTRACTING",
        "EPS",
        "OFT ",
        "USTA",
        "lengthen.v.01",
        "whole.n.02",
        " F",
        "DRA",
        " AL",
        "meat.n.01",
        "FLYI",
        "TSPR",
        "compete.v.01",
        " MER",
        "tire.v.01",
        " FLA",
        " GO",
        "LDED",
        "LDS ",
        "keep.v.07",
        "fly.v.05",
        "ADI",
        "prevent.v.02",
        "NTR",
        "obstruct.v.02",
        "position.n.01",
        "KED",
        "surface.n.01",
        " PUR",
        "spread.v.03",
        "ALL-MERCIFUL",
        "confirm.v.02",
        "HAV",
        "ES",
        "VERY",
        "see.v.17",
        " SUS",
        "HES",
        "grow.v.07",
        "own.v.01",
        "ETC",
        "NOT",
        "see.v.05",
        "LY",
        "OME",
        "OMPA",
        "direct.v.04",
        " ALS",
        " BEN",
        "LAH",
        "change_magnitude.v.01",
        "surely.r.01",
        "IVER",
        "IT",
        "VER",
        " FLY",
        "ONT",
        "ER ",
        "DETH",
        " O",
        "keep.v.19",
        "BSER",
        "accept.v.01",
        "control.v.01",
        "CK",
        "FUL ",
        "observe.v.06",
        "EES",
        " KEE",
        "record.v.01",
        "hold.v.23",
        "E ",
        "RI",
        "perceiver.n.01",
        "mix.v.05",
        "SUST",
        "BAC",
        "close.v.07",
        "goal.n.01",
        "possession.n.02",
        "most.a.01",
        "OVERSEES",
        " MO",
        " BAC",
        "measure.n.02",
        "EVER",
        "OS",
        "OOKE",
        "string_out.v.01",
        "ARD",
        "dame.n.01",
        "military_unit.n.01",
        "interact.v.01",
        "fly.v.06",
        "give.v.03",
        "VERI",
        "causal_agent.n.01",
        "talk_of.v.01",
        " [ ",
        "IEW ",
        "AR",
        "meet.v.02",
        "ALL-",
        "ALO",
        " TRU",
        "GRACIOUS",
        "fly.v.13",
        "induce.v.02",
        "LS",
        "suppress.v.04",
        "hold.v.03",
        "bow_out.v.02",
        "HHOL",
        "ERCI",
        "play.v.01",
        "ETI",
        "withhold.v.02",
        "arrange.v.01",
        "ION",
        "merciful.a.01",
        "fold.v.02",
        "CT",
        "PERC",
        "keep.v.21",
        "OUS",
        "do.v.03",
        "pay.v.01",
        " LO",
        "stop.v.05",
        "ENE",
        "cover.v.01",
        "house.v.02",
        "TR",
        "involve.v.01",
        "determine.v.03",
        "gracious.a.01",
        "sustain.v.06",
        "EVERYTHING",
        "watch.v.04",
        "consider.v.05",
        "] ",
        "RET",
        "help.v.01",
        "KEEP",
        "allah.n.01",
        "OKED",
        "fly.v.03",
        "CAN ",
        "superior.n.01",
        "REGARDED",
        "cultivate.v.01",
        "close_up.v.01",
        " LO ",
        "propel.v.01",
        "inflate.v.01",
        "AH ",
        "continue.v.01",
        "affect.v.02",
        "perceive.v.01",
        " W",
        " WIN",
        "property.n.01",
        "ERTA",
        "RSEE",
        "EING",
        "RULY",
        "VER ",
        " OBS",
        "visit.v.03",
        "dress.v.16",
        "structure.n.01",
        "LD",
        "CHES",
        "READ",
        "shelter.v.01",
        "OLDS",
        "shrink.v.04",
        "save.v.02",
        "LL-",
        "WITHHOLDS",
        "bet.v.02",
        "believe.v.01",
        "-SEE",
        "number.n.02",
        "ERI",
        "CERTAINLY",
        "UREL",
        "SOME",
        "harbor.v.01",
        "gracious.s.04",
        "IVE",
        " A",
        "]",
        "-B",
        "worsen.v.01",
        "fold.v.05",
        "MES",
        "CIFU",
        "do.v.04",
        " IS ",
        "EED",
        "DING",
        "SSIO",
        "YI",
        "turn.v.01",
        "ERY",
        "whole.n.01",
        "impede.v.01",
        "DS ",
        "understand.v.02",
        "ERV",
        "see.v.18",
        "concern.n.01",
        "bear.v.11",
        "R ",
        "HHO",
        "look.v.01",
        "cry.n.01",
        "social_group.n.01",
        "living_thing.n.01",
        "EIVE",
        "fly.v.02",
        "understand.v.01",
        "APPI",
        " SO",
        "SEE ",
        "STR",
        "TCHI",
        "connect.v.01",
        "GO",
        "GHT",
        "HH",
        "merciful.s.02",
        "HDR",
        " WI",
        "beat.v.15",
        "stretch.v.11",
        " V",
        "RTAI",
        "sustain.v.04",
        "REG",
        "IMES",
        "OK",
        "trust.v.01",
        "discontinue.v.01",
        "LA",
        "most.a.02",
        "ER",
        "evaluate.v.02",
        " AR",
        "CAN",
        " BI",
        "-MER",
        "save.v.04",
        "spare.v.01",
        "ETH ",
        "discriminate.v.02",
        "match.v.01",
        " DID",
        "nonaccomplishment.n.01",
        "D_",
        "join.v.04",
        "AD ",
        "STRETCHING",
        "admit.v.01",
        "RAW ",
        "spread.v.10",
        "expand.v.01",
        "CIOU",
        "thing.n.07",
        "close.v.01",
        " PER",
        " COM",
        "GRAC",
        "MPA",
        "L-M",
        "beneficent.a.01",
        "meet.v.05",
        "deny.v.04",
        "THHO",
        "FLYING",
        "AVE",
        "PIN",
        "L-",
        "FI",
        "gain.v.05",
        "RE ",
        " UPH",
        "adult.n.01",
        " CER",
        "ENEF",
        "[ ",
        "flee.v.01",
        "spend.v.02",
        "spread.v.09",
        "move.v.03",
        "visualize.v.01",
        "RY",
        "RVI",
        "HOL",
        "ALLAH",
        "woman.n.01",
        "ILY ",
        " T",
        "SK",
        "impart.v.01",
        "RTA",
        "BSE",
        "UP",
        "FU",
        " OB",
        "ET",
        "aim.v.01",
        " GR",
        "argue.v.01",
        "MERC",
        "withdraw.v.09",
        "D ",
        "fold.v.01",
        "SEEI",
        "small_indefinite_quantity.n.01",
        "suffer.v.02",
        "WA",
        "OKE",
        "VE ",
        "OU",
        "thing.n.02",
        "thing.n.05",
        "close.v.02",
        "EIN",
        "TRU",
        "tour.v.01",
        "HOLDETH",
        "THI",
        "object.n.01",
        "SER",
        "DO ",
        "care.v.02",
        " E",
        "save.v.09",
        " RE",
        "fill.v.09",
        "COMPASSIONATE",
        "DID ",
        "PPIN",
        "HAVE",
        "perform.v.01",
        "close.v.15",
        "TST",
        "PASS",
        "IONA",
        "feel.v.01",
        "feel_for.v.01",
        " WAT",
        "SSI",
        "NL",
        "TRET",
        "COM",
        "thing.n.03",
        " TH",
        "idol.n.01",
        " CLO",
        "NE",
        " C",
        "CHE",
        " NOT",
        "ASS",
        "RVE ",
        "god.n.03",
        "watch.v.06",
        " HAV",
        "OT ",
        "RDE",
        "VES",
        "ETH",
        "implementation.n.02",
        "artifact.n.01",
        " CE",
        "EEN",
        "deem.v.01",
        "TRE",
        "stage.n.03",
        "convey.v.01",
        "confine.v.05",
        "ULY",
        "TIM",
        "provide.v.02",
        "message.n.02",
        "retire.v.08",
        "fly.v.08",
        "transport.v.02",
        "RVES",
        "OBSERVES",
        "separate.v.09",
        "turn_out.v.10",
        "accommodate.v.04",
        "deliver.v.08",
        "DED ",
        "LY ",
        "OBSERVE",
        "experience.v.01",
        "CERT",
        "AC",
        "save.v.03",
        "ONAT",
        "fancify.v.01",
        "carry.v.33",
        "undo.v.01",
        "CK ",
        "change.v.02",
        "AUGH",
        "GHT ",
        "EAD_",
        " IN",
        "food.n.02",
        "matter.n.03",
        "examine.v.02",
        "look.v.03",
        "EN ",
        "UPH",
        "analyze.v.01",
        "DS",
        "BEHOLDER",
        "GS ",
        "AVE ",
        "wait.v.02",
        "apply.v.02",
        "thing.n.04",
        "part.n.03",
        "EEP",
        " EVE",
        "PS",
        "ALL",
        "IRD",
        "AH",
        "equipment.n.01",
        "PER",
        "give_birth.v.01",
        "ULY ",
        "OLDI",
        "recall.v.07",
        " DO ",
        "RCIF",
        "happen.v.01",
        "INDEED",
        "UPHOLD",
        "IEW",
        "expand.v.03",
        "travel.v.01",
        "IOU",
        "INS ",
        "helping.n.01",
        "think.v.03",
        "abstraction.n.06",
        "visit.v.01",
        "BEHO",
        "have.v.17",
        "accept.v.02",
        "wing.n.02",
        "widen.v.04",
        "present.v.02",
        "write.v.08",
        "abridge.v.01",
        "IFUL",
        "get.v.03",
        "LL-M",
        "GA",
        "change_posture.v.01",
        "communication.n.02",
        "HING",
        "retain.v.03",
        "EP",
        "repair.v.01",
        "hold.v.11",
        "group.n.01",
        "LD ",
        "wing.n.07",
        "DEED",
        "CEN",
        "GOD ",
        "grieve.v.01",
        "ES ",
        "hold.v.29",
        "OV",
        "decrease.v.02",
        "cause.v.01",
        "keep.v.01",
        " SKY",
        "BIR",
        "prevent.v.01",
        "RAW",
        "activity.n.01",
        "part.n.02",
        "ATE",
        "receive.v.05",
        "RDS ",
        "UST",
        "most.r.02",
        "EE",
        " ME",
        "come.v.01",
        "TRULY",
        "PAND",
        "compound.v.05",
        "disperse.v.04",
        "affirm.v.02",
        "hold.v.17",
        "unfold.v.03",
        "ceremony.n.03",
        "sell.v.02",
        "capture.v.02",
        "SUS",
        "TE",
        "_OUT",
        "INL",
        "RDS",
        "wing.n.09",
        "undergo.v.01",
        "close.v.12",
        "OBSE",
        " CL",
        "air_unit.n.01",
        "SAV",
        " HOL",
        "NAU",
        "CLOS",
        "indeed.r.02",
        "PHOL",
        "airfoil.n.01",
        "REA",
        "swallow.v.05",
        "ALS",
        "gamble.v.02",
        "vanish.v.05",
        "SURELY",
        "EEN ",
        "FOLDING",
        "OUTS",
        "NONE",
        "UL ",
        " [",
        "OVER",
        "LO ",
        "retain.v.02",
        "TS",
        "circulate.v.02",
        "CONT",
        "process.n.02",
        "CON",
        "SO ",
        " CAN",
        "CE",
        "OUTSPREAD",
        "enlarge.v.01",
        "HI",
        "AW",
        "FLY",
        "contract.v.06",
        "operate.v.03",
        "ON",
        "OSI",
        "grow.v.02",
        "ARDE",
        "ERVE",
        "HD",
        "IR",
        "pull.v.01",
        "salvage.v.01",
        "thing.n.01",
        "CER",
        "RUL",
        "suffice.v.01",
        "god.n.01",
        " IS",
        "stretch.v.01",
        "practice.v.01",
        "increase.v.01",
        "publicize.v.01",
        "keep.v.16",
        "SE",
        "defend.v.02",
        "UPHOLDS",
        "organization.n.01",
        "ENT ",
        "LLA",
        "ALL-BENEFICENT",
        "BEHOLD",
        "visionary.n.02",
        "feeling.n.01",
        " FL",
        "hold.v.14",
        "ED",
        "RIL",
        "OTH",
        "hire.v.01",
        "ERCE",
        "cover.v.03",
        "statement.n.01",
        "OL",
        "deity.n.01",
        "fly.v.04",
        "FOL",
        "SPR",
        "BA",
        "YIN",
        "-M",
        " P",
        "touch.v.01",
        " M",
        "NT",
        "BIRD",
        "complete.v.01",
        "preserve.v.04",
        "SEEN",
        "HDRA",
        " SEE",
        "TA",
        "OUT ",
        "ALOF",
        "WIT",
        "create_by_mental_act.v.01",
        " STR",
        "ST",
        "let_go_of.v.01",
        "EHO",
        "gas.n.02",
        "ND",
        "FLAPPING",
        "BENEFICENT",
        "watch.v.05",
        "see.v.01",
        "fly.v.09",
        "thing.n.08",
        "ERYT",
        "have.v.11",
        "satisfy.v.01",
        "condition.n.01",
        "reserve.v.04",
        " I",
        "nothing.n.01",
        "NLY",
        "ING",
        "aloft.r.02",
        " ST",
        "NG",
        "TCHE",
        "communicate.v.01",
        "UTSP",
        "VERS",
        "organism.n.01",
        "hold.v.13",
        "wings.n.02",
        " ALL",
        "UPHO",
        "EPS ",
        "meet.v.01",
        "W ",
        "watch.v.03",
        "girl.n.01",
        "ACT",
        "close.v.08",
        "delay.v.02",
        "CH",
        "AW ",
        "instrumentality.n.03",
        "ETCH",
        "ALLA",
        "boom.v.05",
        "L-SE",
        "HT ",
        "EER ",
        "ANDI",
        " BEH",
        "RCEI",
        "L ",
        "hold.v.26",
        "close.v.06",
        "animal.n.01",
        "IND",
        "close_up.v.03",
        "SURE",
        "SION",
        "modify.v.01",
        "WING",
        "hour.n.02",
        "produce.v.01",
        "PR",
        " PE",
        "LLAH",
        "ACK ",
        "ONE",
        "LYI",
        "refer.v.02",
        "end.v.02",
        "manipulate.v.02",
        "representational_process.n.01",
        "look.v.02",
        "RACT",
        "action.n.01",
        "VI",
        "RA",
        " WA",
        "end.v.01",
        "scope.n.01",
        "contestant.n.01",
        "emblem.n.02",
        "ERSE",
        "SPREADING",
        "UT "
    ]
}