{
    "VERSE": "43:36",
    "ARABIC": "\u0648\u064e\u0645\u064e\u0646 \u064a\u064e\u0639\u0652\u0634\u064f \u0639\u064e\u0646 \u0630\u0650\u0643\u0652\u0631\u0650 \u0671\u0644\u0631\u0651\u064e\u062d\u0652\u0645\u064e\u0670\u0646\u0650 \u0646\u064f\u0642\u064e\u064a\u0651\u0650\u0636\u0652 \u0644\u064e\u0647\u064f\u06e5 \u0634\u064e\u064a\u0652\u0637\u064e\u0670\u0646\u064b\u0627 \u0641\u064e\u0647\u064f\u0648\u064e \u0644\u064e\u0647\u064f\u06e5 \u0642\u064e\u0631\u0650\u064a\u0646\u064c",
    "ENGLISH": {
        "TRANSLATION_0": "If someone shuts his eyes to the remembrance of the All-Merciful, We assign him a shaytan who becomes his bosom friend -",
        "TRANSLATION_1": "We shall attach to him who goes blind to the remembrance of Ar-Rahman a devil as companion, --\n",
        "TRANSLATION_2": "He who is negligent to remember the Merciful One, to him We assign a satan as his boon companion,\n",
        "TRANSLATION_3": "We shall make satan the companion of whoever ignores the remembrance of the Beneficent God.\n",
        "TRANSLATION_4": "And whoever is averse to the Remembrance of the Most Gracious, We appoint a devil upon him, who stays with him.\n",
        "TRANSLATION_5": "And whosoever Ya`shu (turns away blindly) from the remembrance of the Most Gracious, We appoint for him Shaytan to be a Qarin (a companion) to him.\n",
        "TRANSLATION_6": "And whoever turns himself away from the remembrance of the Beneficent Allah, We appoint for him a Shaitan, so he becomes his associate.\n",
        "TRANSLATION_7": "Whoso blinds himself to the Remembrance of the All-merciful, to him We assign a Satan for comrade;\n",
        "TRANSLATION_8": "And he whose sight is dim to the remembrance of the Beneficent, We assign unto him a devil who becometh his comrade;\n",
        "TRANSLATION_9": "As for one who turns away from the remembrance of the Gracious God, We appoint for him a devil, who will become his intimate companion.\n",
        "TRANSLATION_10": "And whosoever blindeth himself to the admonition of the Compassionate, We assign Unto him a Satan, and he becometh his companion.\n",
        "TRANSLATION_11": "We assign a devil to be the companion of him who turns a blind eye to the remembrance of the All-beneficent.\n",
        "TRANSLATION_12": "If anyone withdraws himself from remembrance of (Allah) Most Gracious, We appoint for him an evil one, to be an intimate companion to him.\n",
        "TRANSLATION_13": "And whosoever turns away (blinds himself) from the remembrance of the Most Beneficent (Allah) (i.e. this Quran and worship of Allah), We appoint for him Shaitan (Satan - devil) to be a Qarin (an intimate companion) to him.\n",
        "TRANSLATION_14": "To whosoever blinds himself from the Remembrance of the Merciful, We shall assign him a satan so he is his companion,\n",
        "TRANSLATION_15": "Whoever shuns the remembrance of the Most Gracious, We assign for him a devil, to be his companion.\n",
        "TRANSLATION_16": "And whoever is blinded from remembrance of the Most Merciful - We appoint for him a devil, and he is to him a companion.\n",
        "TRANSLATION_17": "[43:36] And whoever withdraws from, [whoever] is oblivious, to the Remembrance of the Compassionate One, namely, the Qur\u2019\u0101n, We assign, We produce, for him a devil and he becomes his companion, never leaving his side.\n",
        "TRANSLATION_18": "568 (And he whose sight is dim to the remembrance of the Beneficent) and he who is blind to the declaration of the divine Oneness and Scripture of the Beneficent, (We assign unto him a devil who becometh his comrade) in the life of the world and in the Fire;\n"
    },
    "CROSS_REFERENCE": {
        "QURAN": [
            "43:36",
            "2:160",
            "67:29",
            "20:109",
            "4:38",
            "19:44",
            "26:5",
            "26:210",
            "25:60",
            "26:221"
        ],
        "BIBLE": [
            "prophets:hosea:11:8",
            "prophets:zephaniah:3:20",
            "prophets:jeremiah:50:3",
            "prophets:jeremiah:31:13",
            "writings:psalms:21:13",
            "torah:exodus:23:27",
            "prophets:ezekiel:5:14",
            "torah:genesis:35:3",
            "torah:deuteronomy:4:25",
            "writings:ezra:5:5"
        ]
    },
    "FEATURES": [
        "NO",
        "IOUS",
        "politician.n.02",
        " SA",
        "total.v.01",
        "ACI",
        "ACH_",
        "DI",
        "POI",
        "EFI",
        "IGNO",
        "PAN",
        "spiritual_being.n.01",
        "RSE",
        "most.r.01",
        "request.v.01",
        "UN",
        "SOM ",
        "NT ",
        "make.v.32",
        "remember.v.05",
        "DRAW",
        "REME",
        "OD ",
        "look.n.02",
        "opinion.n.01",
        "SATA",
        "ED ",
        "one.n.01",
        " D",
        "MPAN",
        "OSOE",
        "OM ",
        "view.n.03",
        "make.v.36",
        "call_on.v.01",
        "SAT",
        "unpleasant_person.n.01",
        "disengage.v.01",
        "INT ",
        "YE",
        "CIO",
        " GRA",
        "exocrine_gland.n.01",
        "WITH",
        " SHU",
        " BL",
        "WORS",
        "R-RA",
        "DEVI",
        "retire.v.02",
        "go.v.25",
        "SO",
        " ONE",
        "N ",
        "leave.v.08",
        "achieve.v.01",
        "remove.v.01",
        "AR-R",
        "percept.n.01",
        "make.v.01",
        "ONA",
        "integer.n.01",
        "sagacity.n.01",
        "HAYT",
        "ON ",
        "associate.n.01",
        "OMP",
        "ST ",
        "HUTS",
        "UTS",
        "order.v.05",
        "antipathetic.s.01",
        "associate.n.03",
        "L-B",
        " IGN",
        "location.n.01",
        "IL ",
        "succeed.v.01",
        "ANYONE",
        "transfer.v.02",
        "YTA",
        "ANY",
        "remember.v.03",
        "WHOS",
        "OD",
        " UNT",
        "turn.v.09",
        "away.r.04",
        "MONI",
        "friend.n.05",
        "EMEM",
        "-BE",
        "criticism.n.01",
        "COMPANION",
        "transgression.n.01",
        "SHAI",
        "entity.n.01",
        "OME ",
        "persuade.v.02",
        "fasten.v.01",
        "IGH",
        "EMBR",
        "AV",
        "ILL ",
        "develop.v.14",
        "do.v.08",
        "NAT",
        "attach_to.v.01",
        "RCI",
        "search.v.04",
        "plow.v.01",
        "TTAC",
        " GOD",
        "remember.v.02",
        "draw.v.04",
        "turn.v.17",
        " APP",
        "IO",
        "ability.n.02",
        "BO",
        "make.v.46",
        " SI",
        "CH_T",
        "event.n.01",
        "change.v.01",
        "intuition.n.02",
        " R",
        "DM",
        "HOS",
        "become.v.02",
        "ECO",
        "remember.v.07",
        "admonition.n.02",
        "AY ",
        " QU",
        "AD",
        "AS",
        " BOO",
        " Q",
        "H_TO",
        "ignore.v.05",
        "EN",
        "move.v.15",
        "thing.n.12",
        "monster.n.04",
        "utterance.n.01",
        "CIA",
        "MERCIFUL",
        "IGHT",
        " WIT",
        "state.n.02",
        "identify.v.01",
        "adjourn.v.02",
        "communist.n.02",
        "stay.v.09",
        "US ",
        "LL",
        "LI",
        "SHAL",
        "HU",
        "make.v.33",
        "AL",
        "RAHM",
        "FICE",
        "include.v.01",
        "impression.n.01",
        "ASSIGN",
        "make.v.25",
        "LAH ",
        "make.v.02",
        "external_body_part.n.01",
        "attention.n.01",
        " SH",
        "assistant.n.01",
        "CENT",
        "RACI",
        "create.v.05",
        "-BEN",
        "FRIE",
        "EYE",
        "persist.v.03",
        "reject.v.01",
        "DET",
        "NEFI",
        "breast.n.01",
        "NTO",
        "blind.n.01",
        "body_part.n.01",
        "MEMB",
        "SSO",
        "falsehood.n.01",
        "RAN",
        "die.v.01",
        "SOM",
        "go.v.10",
        "AN",
        " GOE",
        "guarantee.v.02",
        "OM",
        "MRAD",
        "IGN ",
        "COMP",
        "suffer.v.03",
        "black.s.04",
        "away.r.10",
        "turn.v.23",
        "TI",
        "auditory_communication.n.01",
        "ONE ",
        "LIG",
        "GR",
        "OSOM",
        " AR-",
        "darken.v.03",
        "turn.v.22",
        "constitute.v.01",
        "leader.n.01",
        "meet.v.04",
        "-ME",
        "COME",
        "PP",
        "re-create.v.01",
        "move.v.02",
        "ORES",
        "change_by_reversal.v.01",
        "think.v.01",
        "inner.s.03",
        "PA",
        "OES",
        "URN",
        "EVE",
        "till.v.01",
        "physical_entity.n.01",
        "mention.v.01",
        "TH",
        "commend.v.05",
        "make.v.16",
        "AK",
        "OSO",
        "go.v.05",
        "ATTACH_TO",
        "MER",
        "BECOMES",
        "make.v.42",
        "PAS",
        " BO",
        "unit.n.04",
        "AYT",
        "SI",
        " YA ",
        "lay_down.v.01",
        "MRA",
        "I.E",
        "ADMO",
        "EVI",
        "DR",
        "appeal.v.02",
        "love.n.01",
        "indispose.v.03",
        "sight.n.03",
        " FO",
        "one.n.02",
        "IFU",
        "RNS",
        " SIG",
        "dim.s.02",
        " UN",
        "ONI",
        "ND ",
        "AP",
        "negligent.a.01",
        "intimate.s.04",
        "adoption.n.01",
        "BOS",
        "comrade.n.02",
        "IM",
        "excrete.v.01",
        "AITA",
        "SHAY",
        "BEC",
        "SOMEONE",
        "DIM",
        "BR",
        "effect.v.01",
        "companion.n.01",
        "NEGL",
        " IG",
        " ATT",
        "SIGHT",
        "dimmed.a.01",
        "OO",
        "remember.v.04",
        "turn.v.07",
        "function.v.01",
        "be.v.03",
        "IL",
        "signal.n.01",
        "quell.v.02",
        "friend.n.01",
        "be.v.01",
        "BOO",
        "PPOI",
        "proceed.v.04",
        "TTA",
        "BENE",
        "make.v.41",
        "use.v.01",
        "MOS",
        "orientation.n.02",
        "LIND",
        "hole.n.02",
        "shape.v.03",
        "SOEV",
        "NTIM",
        "retire.v.01",
        "ALL ",
        "VIL",
        "TAY",
        "blind.s.03",
        "METH",
        "CIF",
        "IE",
        "ERS",
        "RAC",
        "distinguish.v.01",
        "UR",
        "exit.v.01",
        "FRIEND",
        "AKE ",
        " INT",
        "fortune.n.04",
        "cloth_covering.n.01",
        "tidy.v.01",
        "dismiss.v.01",
        "UTS ",
        "condition.n.03",
        " N",
        "sound.v.02",
        "person.n.01",
        "NORE",
        " B",
        "change_shape.v.01",
        " EVI",
        "OST ",
        "devolve.v.03",
        "eyes.n.01",
        "OMEO",
        "TIO",
        "AN ",
        "EV",
        "YS",
        " MOS",
        "GN ",
        "HUN",
        "gain.v.08",
        "bad.n.01",
        "stay.v.02",
        "reach.v.01",
        " MAK",
        "DE",
        "withdraw.v.01",
        "blind.n.02",
        "AWS",
        "L-BE",
        "S ",
        "BE",
        "_O",
        " CO",
        " ANY",
        "FOR_",
        "QARI",
        "MET",
        "turn.v.10",
        "wrongdoing.n.02",
        "AVER",
        "beneficent.s.02",
        "evil.n.03",
        "YES",
        "create_from_raw_material.v.01",
        "BOON",
        "QURAN",
        "HA",
        "generate.v.01",
        "_TO",
        "about.r.07",
        "OEVE",
        "AHM",
        "L-ME",
        "appoint.v.02",
        " DEV",
        "RIEN",
        "NDS",
        "turn.v.19",
        "advocate.n.01",
        "TT",
        "NEF",
        "distribute.v.01",
        "UNT",
        "retreat.v.04",
        "stay.v.01",
        "FIC",
        " BLI",
        "creation.n.02",
        " STA",
        "OR",
        "OE",
        " DI",
        "carry_through.v.01",
        "make.v.47",
        "NDET",
        "HAY",
        "visual_percept.n.01",
        "seclude.v.01",
        "manage.v.02",
        "act.v.01",
        "SIGN",
        "OUS ",
        "CH_",
        "TUR",
        "INTIMATE",
        "UL",
        " EV",
        "-RA",
        "OMRA",
        "END",
        "eye.n.03",
        "make.v.35",
        "belief.n.01",
        "stay.v.05",
        "US",
        "RS",
        "position.v.01",
        "evil.n.02",
        "SHU ",
        "URAN",
        "score.v.01",
        "symbol.n.01",
        "NEG",
        "eye.n.02",
        "RE",
        "BER ",
        "HOSO",
        "make.v.03",
        "SHU",
        "BRA",
        " ADM",
        "BECOME",
        "ignore.v.03",
        "get.v.01",
        "ME",
        "digit.n.01",
        "away.r.01",
        "HUT",
        "HT",
        " DIM",
        "last_out.v.01",
        "URNS",
        " WH",
        "FUL",
        " AWA",
        "NYON",
        "initiate.v.02",
        "SA",
        "make.v.49",
        "INDE",
        "put.v.04",
        "TAN",
        "TH ",
        "IA",
        "KE",
        "disapproval.n.02",
        "CI",
        "attribute.n.02",
        "LIGE",
        "HMAN",
        "indefinite_quantity.n.01",
        "SIG",
        "TE ",
        "LL ",
        "EON",
        "blind.n.03",
        "RAH",
        "for_one.r.01",
        "IGN",
        "RES",
        "SHUNS",
        "GOD",
        "representation.n.02",
        "concept.n.01",
        "YE ",
        "expel.v.01",
        "R_O",
        "calculate.v.01",
        "BLINDLY",
        "off.r.02",
        "NDL",
        "compassionate.a.01",
        " BE",
        "region.n.03",
        "koran.n.01",
        "SOCI",
        "choose.v.01",
        "RC",
        " BEC",
        "cognition.n.01",
        "sight.n.01",
        "R_",
        "ITHD",
        "blend.v.02",
        "NCE ",
        "APP",
        "RNS ",
        "VE",
        "ICEN",
        "ITIO",
        "eye.n.05",
        " AVE",
        "NA",
        "OEV",
        "SHI",
        "H_",
        " AP",
        "protective_covering.n.01",
        "troublemaker.n.01",
        "MO",
        "faculty.n.01",
        " U",
        "spirit.n.04",
        " Y",
        "misrepresentation.n.01",
        "WHOSO",
        "UNS ",
        "YT",
        "good_fortune.n.01",
        "bosom.n.03",
        "ATE ",
        "INTI",
        "SHAYTAN",
        "benignant.s.02",
        "AI",
        "go.v.23",
        "sour.v.01",
        "content.n.05",
        "courteous.s.01",
        "award.n.02",
        "EM",
        "UNS",
        "NATE",
        "NS",
        "sensitivity.n.01",
        "IM ",
        "neglect.v.04",
        "IN",
        "memory.n.03",
        "M ",
        "organ.n.01",
        "LL-B",
        "GRA",
        "H ",
        "estimate.v.01",
        "EMB",
        "RSE ",
        "VIL ",
        "Y ",
        "handle.v.04",
        "change_state.v.01",
        "GLIG",
        "arrogate.v.02",
        "UT",
        "transfer.v.05",
        "YO",
        "WI",
        "NION",
        "ORSH",
        "make.v.43",
        "SIGH",
        "familiar.s.04",
        "MR",
        "ally.n.02",
        "MES ",
        "ICE",
        "RADE",
        ".E ",
        "happening.n.01",
        "WITHDRAWS",
        "make.v.19",
        "SS",
        "exclude.v.02",
        "QURA",
        "EONE",
        "away.r.02",
        "HO",
        "THD",
        "ITI",
        "IGE",
        "ERC",
        "banish.v.01",
        "stool.v.04",
        "AT",
        "IMAT",
        "emotion.n.01",
        "WILL",
        "aside.r.06",
        "MAKE",
        "OON ",
        "ASSI",
        "assign.v.02",
        " ON",
        " G",
        "OST",
        "make.v.27",
        "OCI",
        "EGLI",
        "send.v.01",
        "ENT",
        "MEO",
        "socialist.n.01",
        "ITAN",
        "AYTA",
        "EFIC",
        "IND ",
        "DED",
        "compass.n.03",
        " DE",
        "I.",
        "away.r.06",
        "batch.n.02",
        "MBER",
        "equal.v.01",
        "OON",
        "isolate.v.01",
        " FR",
        "isolation.n.01",
        " NEG",
        "PPO",
        "BLINDETH",
        "act.n.02",
        "TO",
        "admonition.n.01",
        "definite_quantity.n.01",
        "inhere_in.v.01",
        "EF",
        "EVIL",
        "GH",
        "fit.v.07",
        " SOM",
        "amount.v.01",
        "psychological_feature.n.01",
        "THDR",
        "O ",
        "BEN",
        "NDE",
        "MOST",
        "effigy.n.01",
        "T ",
        "turn.v.14",
        "disown.v.02",
        "supply.v.01",
        "_T",
        "INT",
        "DEVIL",
        "NCE",
        "MAN ",
        "turn.v.26",
        "OR_O",
        "ACIO",
        " AD",
        "act.v.02",
        "make.v.38",
        "make.v.14",
        "develop.v.10",
        "BOSO",
        "IS ",
        "MP",
        "BOSOM",
        "AYS",
        "CO",
        "sense.n.03",
        "idea.n.01",
        "DMON",
        "INDS",
        "DEV",
        "convey.v.03",
        "ORE",
        "AYS ",
        "bosom.n.01",
        "PO",
        "seduce.v.01",
        "compare.v.02",
        "STA",
        "immorality.n.01",
        " S",
        "TURN",
        "WORSHIP",
        "YA ",
        "take.v.08",
        "OMET",
        "BLI",
        "exhaust.v.05",
        "eye.n.01",
        "QU",
        "PANI",
        "TAYS",
        "ITH",
        "companion.n.03",
        "leave_office.v.01",
        "start.v.09",
        "IC",
        "STAYS",
        "IS",
        "bide.v.01",
        "put.v.01",
        "AWS ",
        "BLIND",
        "make.v.34",
        "dense.s.04",
        "ADE",
        "cook.v.02",
        "SIO",
        "IF",
        "MPAS",
        "MATE",
        "shaitan.n.01",
        "basic_cognitive_process.n.01",
        "REMEMBER",
        "NY",
        "MEM",
        "position.n.03",
        "NE ",
        "EG",
        "AR-",
        "IEN",
        "FO",
        "ONIT",
        "WIL",
        "assemble.v.03",
        "SHUTS",
        "perpetrate.v.01",
        "breast.n.02",
        "ANCE",
        "make.v.24",
        " AW",
        "RN",
        "GLI",
        "NS ",
        "take.v.27",
        "GN",
        "subterfuge.n.01",
        "sensing.n.02",
        "SATAN",
        "devil.n.03",
        "turn.v.18",
        "whole.n.02",
        "blind.v.01",
        " F",
        "DRA",
        " AL",
        "OINT",
        "turn.v.11",
        "assign.v.07",
        "RIN",
        "tire.v.01",
        " MER",
        " GO",
        "large_indefinite_quantity.n.01",
        "MAT",
        "worship.n.02",
        "ANIO",
        " QUR",
        "prevent.v.02",
        " MA",
        "OES ",
        "blind.v.03",
        "ALL-MERCIFUL",
        "WOR",
        "TO ",
        "ANYO",
        "HAIT",
        "away.r.07",
        "ES",
        "see.v.05",
        "go.v.03",
        "go.v.28",
        "LY",
        "R_ON",
        "separation.n.01",
        "OME",
        "OMPA",
        "direct.v.04",
        " BEN",
        "make.v.48",
        "LAH",
        "YA",
        "evil_spirit.n.01",
        "change_magnitude.v.01",
        " FOR",
        "IT",
        "establish.v.02",
        "VER",
        "impute.v.01",
        "DE ",
        "sense_organ.n.01",
        "ER ",
        "harmonize.v.01",
        "DETH",
        "U ",
        "christian.n.01",
        " O",
        "hurt.v.02",
        "CIAT",
        "control.v.01",
        "advice.n.01",
        "FUL ",
        "DMO",
        "ILL",
        "aptitude.n.01",
        "cozy.s.02",
        "DL",
        " NE",
        "MA",
        "exclamation.n.01",
        "E ",
        "run.v.05",
        "RI",
        "GEN",
        "HAL",
        "most.a.01",
        " MO",
        "ANI",
        "measure.n.02",
        "EVER",
        "SHUN",
        "OS",
        "GNO",
        "intimate.s.01",
        "ATTA",
        "UNTO",
        "interact.v.01",
        "give.v.03",
        "causal_agent.n.01",
        "YTAN",
        "associate.n.04",
        "AR",
        "FR",
        "blessing.n.01",
        "aside.r.02",
        "ALL-",
        "GRACIOUS",
        "GL",
        "SH",
        "induce.v.02",
        "hold.v.03",
        "bow_out.v.02",
        "ERCI",
        "decide.v.01",
        "IGNORES",
        "HUNS",
        "become.v.01",
        "arrange.v.01",
        "run_low.v.01",
        "make.v.44",
        "HU ",
        "ION",
        "merciful.a.01",
        "OUS",
        "claim.v.02",
        "DLY",
        "do.v.03",
        "mammary_gland.n.01",
        "GE",
        "acquaintance.n.03",
        "ENE",
        "determine.v.03",
        "IN ",
        "IP ",
        "EGL",
        "gracious.a.01",
        "become.v.03",
        "BLINDS",
        "devil.n.02",
        " TUR",
        "allah.n.01",
        "supporter.n.01",
        "center.n.01",
        "superior.n.01",
        "ACH",
        "close_up.v.01",
        "intimate.s.06",
        "YON",
        "AH ",
        "NOR",
        "POIN",
        " W",
        "associate.v.01",
        "NI",
        "form.v.02",
        "turn.v.13",
        "OIN",
        "OC",
        "ignore.v.01",
        "VER ",
        "CE ",
        "AKE",
        "appoint.v.03",
        "unwelcome_person.n.01",
        "blindly.r.02",
        "support.n.02",
        "make.v.45",
        "ADM",
        "ARIN",
        "LL-",
        "STAY",
        "screen.n.04",
        "display.n.05",
        "HAI",
        "number.n.02",
        "EYE ",
        "SOME",
        "sight.n.04",
        "gracious.s.04",
        " A",
        "fit.v.02",
        "REM",
        "stay_in_place.v.01",
        "confidant.n.01",
        "-B",
        "worsen.v.01",
        "MES",
        "CIFU",
        "RSH",
        " IS ",
        "DLY ",
        "peer.n.01",
        "SSIO",
        " YA",
        "turn.v.01",
        "survive.v.01",
        "GOES",
        "whole.n.01",
        "make.v.37",
        "stay.v.10",
        " REM",
        "AWA",
        "DS ",
        "go.v.09",
        "R ",
        "HIP",
        "living_thing.n.01",
        "BRAN",
        "MAK",
        " SO",
        "pass.v.01",
        "connect.v.01",
        "GO",
        "appoint.v.01",
        "GHT",
        "merciful.s.02",
        "R-R",
        "OI",
        "HDR",
        " WI",
        "make.v.31",
        "memorial.n.01",
        "MEON",
        "fail.v.04",
        "blindly.r.01",
        "reason.v.03",
        "equip.v.01",
        "make.v.15",
        "bosom.n.02",
        "worship.n.01",
        "attach.v.01",
        "discontinue.v.01",
        "go.v.22",
        "LA",
        "most.a.02",
        "BER",
        "ER",
        "evaluate.v.02",
        " AR",
        "dim.s.01",
        "-MER",
        "ADE ",
        "NTO ",
        "ETH ",
        "discriminate.v.02",
        "wisdom.n.03",
        "sensory_activity.n.01",
        "match.v.01",
        "COMR",
        "devil.v.02",
        "modality.n.03",
        "OCIA",
        "CIOU",
        "close.v.01",
        " COM",
        "GRAC",
        "bequeath.v.01",
        "A ",
        "NDLY",
        "MPA",
        "L-M",
        "quality.n.01",
        "sight.n.02",
        "beneficent.a.01",
        "AVE",
        "traveler.n.01",
        "AIT",
        "SHA",
        "turn.v.08",
        "L-",
        "OMR",
        "OMES",
        "FI",
        "gain.v.05",
        "ENEF",
        "IMA",
        "APPO",
        "WS ",
        "move.v.03",
        "ALLAH",
        " AS",
        "NITI",
        " T",
        "RANC",
        "EMBE",
        "heart.n.01",
        "go.v.16",
        "EME",
        "MBRA",
        " I.E",
        "LIN",
        "TURNS",
        "FU",
        "NC",
        "ANC",
        "ET",
        "aim.v.01",
        "NEGLIGENT",
        "BL",
        "KE ",
        "-RAH",
        "think_of.v.04",
        "YS ",
        " GR",
        "turn.v.06",
        "gland.n.01",
        "MERC",
        "withdraw.v.09",
        "D ",
        "proceed.v.02",
        "SOC",
        "WA",
        "OU",
        "WHOSOEVER",
        "close.v.02",
        "away.r.08",
        " AT",
        "companion.n.02",
        "proposal.n.01",
        "IATE",
        "rebuke.n.01",
        "area.n.01",
        "YONE",
        "delegate.v.02",
        "object.n.01",
        "AY",
        "disappear.v.01",
        "assign.v.08",
        " QAR",
        "WS",
        "AR-RAHMAN",
        " E",
        "discolor.v.03",
        "BLINDED",
        " RE",
        "COMPASSIONATE",
        "act.v.03",
        "perform.v.01",
        "IONA",
        "PASS",
        "feel.v.01",
        "feel_for.v.01",
        "SSI",
        "AHMA",
        "TU",
        "MBR",
        "RSHI",
        "COM",
        "make.v.18",
        "academic_degree.n.01",
        " ASS",
        "WH",
        "idol.n.01",
        "give.v.08",
        " WOR",
        "NE",
        " C",
        "ASS",
        "RAN ",
        "RIN ",
        "god.n.03",
        "ARI",
        "ETH",
        "artifact.n.01",
        "_ONE",
        "sight.n.05",
        "RIE",
        "DIM ",
        "ME ",
        "NTI",
        "embrace.n.03",
        "develop.v.13",
        "plump.v.04",
        "TIM",
        "provide.v.02",
        "message.n.02",
        "retire.v.08",
        "BECO",
        "worker.n.01",
        "treat.v.01",
        "subordinate.n.01",
        "satan.n.01",
        "DED ",
        "LY ",
        "AC",
        "ONAT",
        "people.n.01",
        "religious_person.n.01",
        " AV",
        "brother.n.04",
        "displease.v.01",
        ".E",
        "SE ",
        "change.v.02",
        "GHT ",
        "EC",
        " IN",
        "MB",
        "MAN",
        "RAD",
        "examine.v.02",
        "P ",
        "DS",
        "covering.n.02",
        "blind.a.01",
        "_ON",
        "HM",
        "part.n.03",
        "NYO",
        "representation.n.01",
        "attitude.n.01",
        "AVERSE",
        "ATA",
        "TAN ",
        "TACH",
        "rifle.v.02",
        "ALL",
        "AH",
        "BECOMETH",
        "belong.v.03",
        "TS ",
        "SHIP",
        "SSOC",
        "recall.v.07",
        "head.v.01",
        "TAC",
        "RCIF",
        "cause_to_be_perceived.v.01",
        "happen.v.01",
        " WO",
        "GENT",
        "travel.v.01",
        "RES ",
        "IOU",
        "think.v.03",
        "-R",
        "abstraction.n.06",
        "GNOR",
        "have.v.17",
        "assign.v.04",
        "MBE",
        "IFUL",
        " I.",
        "LL-M",
        "INDL",
        "communication.n.02",
        "HALL",
        "run.v.03",
        "blessing.n.02",
        "group.n.01",
        "genie.n.01",
        "capability.n.03",
        "work.v.05",
        "SHAITAN",
        " EY",
        "grieve.v.01",
        "CEN",
        "GOD ",
        "stay.v.04",
        "IG",
        "ES ",
        " EYE",
        "cause.v.01",
        "RAW",
        "prevent.v.01",
        "activity.n.01",
        "ATE",
        "most.r.02",
        " FRI",
        "_TO ",
        "remember.v.01",
        " ME",
        " QA",
        "NDED",
        "go.v.19",
        "TE",
        "turn.v.20",
        "QA",
        "OSO ",
        "know-how.n.01",
        "flex.v.05",
        "SSIG",
        "evil.n.01",
        "swallow.v.05",
        "ORS",
        "APPOINT",
        " SHA",
        "exteroception.n.01",
        "EYES",
        "COMRADE",
        "WAY",
        "UL ",
        "ASSO",
        "TS",
        "blind.s.02",
        "twist.v.10",
        "FOR",
        "privacy.n.02",
        "ADMONITION",
        "process.n.02",
        "R-",
        "SO ",
        "CE",
        "AW",
        "HI",
        "OR_",
        "I.E ",
        "make.v.08",
        "GOE",
        "operate.v.03",
        "IEND",
        "ON",
        "QAR",
        "grow.v.02",
        "ASSOCIATE",
        "senesce.v.01",
        "HD",
        "SHUT",
        "move.v.13",
        "REMEMBRANCE",
        "transmit.v.04",
        "god.n.01",
        " IS",
        "approval.n.04",
        "increase.v.01",
        "FRI",
        "SE",
        "SHALL",
        "accompaniment.n.01",
        "ENT ",
        "LLA",
        "produce.v.02",
        "ALL-BENEFICENT",
        "hellion.n.01",
        "SOE",
        "feeling.n.01",
        "ED",
        "check.v.07",
        "statement.n.01",
        "deity.n.01",
        "stop.v.03",
        "-M",
        "go.v.02",
        "QARIN",
        "touch.v.01",
        " M",
        "commemorate.v.02",
        "NT",
        "BE ",
        "reach.v.07",
        "turn.v.04",
        "complete.v.01",
        " SAT",
        "HDRA",
        "TA",
        "WIT",
        "away.r.09",
        "opening.n.10",
        "create_by_mental_act.v.01",
        "ION ",
        "ST",
        "let_go_of.v.01",
        "HIP ",
        "ND",
        "BENEFICENT",
        "name.v.03",
        "ATT",
        " I",
        "IAT",
        "IGEN",
        " ST",
        "annoy.v.01",
        "YES ",
        "associate_degree.n.01",
        "WAY ",
        "NDS ",
        "communicate.v.01",
        "turn.v.16",
        "URA",
        "ATAN",
        "VERS",
        "organism.n.01",
        "remembrance.n.01",
        " BOS",
        " ALL",
        "RAWS",
        "transform.v.02",
        "attendant.n.01",
        "NIT",
        "shun.v.01",
        "IP",
        "CH",
        "TIMA",
        "FOR_ONE",
        "ALLA",
        "HT ",
        "avoid.v.01",
        "ECOM",
        "END ",
        "AWAY",
        "construct.v.01",
        "L ",
        " WIL",
        "stay.v.06",
        "MON",
        " BE ",
        "ITA",
        "WHO",
        "make.v.30",
        "IND",
        "NIO",
        "EY",
        "SION",
        "injure.v.01",
        "QUR",
        "BLIN",
        "LLAH",
        "ONE",
        "blind.v.02",
        "aid.n.02",
        "end.v.02",
        " WHO",
        "manipulate.v.02",
        "look.v.02",
        "HMA",
        "VI",
        "RA",
        "recognition.n.03",
        "H_T",
        "transform.v.03",
        "end.v.01",
        "EO",
        " TU",
        "WO",
        "ERSE",
        "TION",
        " AN"
    ]
}