{
    "VERSE": "18:20",
    "ARABIC": "\u0625\u0650\u0646\u0651\u064e\u0647\u064f\u0645\u0652 \u0625\u0650\u0646 \u064a\u064e\u0638\u0652\u0647\u064e\u0631\u064f\u0648\u0627\u06df \u0639\u064e\u0644\u064e\u064a\u0652\u0643\u064f\u0645\u0652 \u064a\u064e\u0631\u0652\u062c\u064f\u0645\u064f\u0648\u0643\u064f\u0645\u0652 \u0623\u064e\u0648\u0652 \u064a\u064f\u0639\u0650\u064a\u062f\u064f\u0648\u0643\u064f\u0645\u0652 \u0641\u0650\u0649 \u0645\u0650\u0644\u0651\u064e\u062a\u0650\u0647\u0650\u0645\u0652 \u0648\u064e\u0644\u064e\u0646 \u062a\u064f\u0641\u0652\u0644\u0650\u062d\u064f\u0648\u0653\u0627\u06df \u0625\u0650\u0630\u064b\u0627 \u0623\u064e\u0628\u064e\u062f\u064b\u0627",
    "ENGLISH": {
        "TRANSLATION_0": "for if they find out about you they will stone you or make you revert to their religion and then you will never have success.'",
        "TRANSLATION_1": "If they come to know of you they will stone you to death, or force you to go back to their creed; then you will never succeed.\"\n",
        "TRANSLATION_2": "For if they should come upon us, they will stone us to death or force us to revert to their faith whereafter we shall never prosper.\"\n",
        "TRANSLATION_3": "they would certainly stone us to death or force us to follow their religion. Then we shall never be able to have everlasting happiness.\"\n",
        "TRANSLATION_4": "\u201cIndeed if they come to know about you, they will stone you or turn you back to their religion \u2013 and if so, you will never prosper.\u201d\n",
        "TRANSLATION_5": "For, if they come to know of you, they will stone you or turn you back to their religion; and in that case you will never be successful.\"\n",
        "TRANSLATION_6": "For surely if they prevail against you they would stone you to death or force you back to their religion, and then you will never succeed.\n",
        "TRANSLATION_7": "If they should get knowledge of you they will stone you, or restore you to their creed, then you will not prosper ever.\n",
        "TRANSLATION_8": "For they, if they should come to know of you, will stone you or turn you back to their religion; then ye will never prosper.\n",
        "TRANSLATION_9": "for if they find you out, they will stone you to death, or force you back into their faith. In that case you would never prosper.\"\n",
        "TRANSLATION_10": "Verily they, if they come to know of you, would stone you or make you revert to their faith, and lo! then ye will never fare well.\n",
        "TRANSLATION_11": "Indeed should they prevail over you, they will [either] stone you [to death], or force you back into their creed, and then you will never be saved. \u2019\n",
        "TRANSLATION_12": "For if they should come upon you, they would stone you or force you to return to their cult, and in that case ye would never attain prosperity.\"\n",
        "TRANSLATION_13": "For if they come to know of you, they will stone you (to death or abuse and harm you) or turn you back to their religion, and in that case you will never be successful.\"\n",
        "TRANSLATION_14": "For, if they appear in front of you, they will stone you to death or restore you to their religion. Then you will never prosper'\n",
        "TRANSLATION_15": "\u201cIf they discover you, they will stone you, or force you back into their religion; then you will never be saved.\u201d\n",
        "TRANSLATION_16": "Indeed, if they come to know of you, they will stone you or return you to their religion. And never would you succeed, then - ever.\"\n",
        "TRANSLATION_17": "[18:20] For indeed if they should come to know of you, they will [either] stone you, kill you by stoning, or make you return to their creed, and then, if you do return to their creed, you will never prosper\u2019.\n",
        "TRANSLATION_18": "(For they, if they) the Magians (should come to know of you, will stone you) kill you (or turn you back to their religion) Zoroastrianism; (then ye will never prosper) you will never escape from Allah's punishment.\n"
    },
    "CROSS_REFERENCE": {
        "QURAN": [
            "18:20",
            "18:3",
            "33:65",
            "5:24",
            "37:137",
            "24:17",
            "37:24",
            "7:90",
            "11:33",
            "9:83"
        ],
        "BIBLE": [
            "prophets:ezekiel:35:9",
            "writings:ezra:5:5",
            "prophets:isaiah:55:11",
            "torah:exodus:23:27",
            "writings:job:41:20",
            "writings:psalms:106:8",
            "prophets:zephaniah:3:20",
            "prophets:jeremiah:31:13",
            "prophets:ii%20samuel:23:5",
            "writings:psalms:21:13"
        ]
    },
    "FEATURES": [
        "NO",
        "AIN",
        "LE",
        " SA",
        "kill.v.01",
        "total.v.01",
        "FTER",
        " WE",
        " CAS",
        "DI",
        "RLA",
        "force.n.01",
        "THAT",
        "G ",
        "STI",
        "inform.v.01",
        "KNOWLEDGE",
        "CRE",
        "plant.n.02",
        "LLO",
        "request.v.01",
        "state.v.01",
        "answer.v.01",
        "COME_UPON",
        "NT ",
        "make.v.32",
        "reelect.v.01",
        " KNO",
        " SO ",
        "ED ",
        " D",
        "exist.v.01",
        "DGE ",
        "HAR",
        "death.n.01",
        "cult.n.05",
        "ONT ",
        "restore.v.01",
        "WL",
        "make.v.36",
        "call_on.v.01",
        "REED",
        "ASE",
        "consume.v.02",
        "predominate.v.01",
        "YE",
        "copulate.v.01",
        "DEE",
        "ULD ",
        "everlasting.n.01",
        "know.v.07",
        " RET",
        "\u201c ",
        "LEDG",
        "TTAI",
        "SO",
        "N ",
        "know.v.11",
        "pathological_state.n.01",
        "achieve.v.01",
        "regenerate.v.01",
        "remove.v.01",
        " WHE",
        "PPEA",
        "E_T",
        "flower.n.01",
        " YE",
        "make.v.01",
        "LOW",
        "crystal.n.01",
        "ON ",
        "recover.v.03",
        "CCES",
        "order.v.05",
        "D_OU",
        "GIO",
        "determine.v.08",
        "impel.v.01",
        "containerful.n.01",
        "IL ",
        "STON",
        "success.n.02",
        "succeed.v.01",
        "OUT",
        "transfer.v.02",
        "composite.n.02",
        "APPEAR",
        "UPO",
        "return.v.05",
        "fact.n.01",
        "turn.v.09",
        "SUCCESS",
        "ETUR",
        "appear.v.07",
        "TOR",
        "discover.v.03",
        "entity.n.01",
        "follow.v.18",
        "bed_linen.n.01",
        "SUC",
        "RELY",
        "violence.n.01",
        "refrain.v.01",
        "persuade.v.02",
        "case.n.19",
        "AIN ",
        "REST",
        "ill_health.n.01",
        "ILL ",
        "ME_T",
        "AV",
        "do.v.08",
        "develop.v.14",
        "PI",
        "plow.v.01",
        "tell.v.02",
        "OWLE",
        "ULD",
        "draw.v.04",
        " APP",
        "turn.v.17",
        "ME_",
        "BUSE",
        "IO",
        "return.v.16",
        "make.v.46",
        "VED ",
        "event.n.01",
        "FAITH",
        "change.v.01",
        " R",
        "surveil.v.01",
        "HOUL",
        "regenerate.v.04",
        "denote.v.02",
        "SCO",
        "_TH",
        "ESSF",
        "discover.v.07",
        "VED",
        "become.v.02",
        "REVE",
        "come_to.v.03",
        "discover.v.04",
        "VAI",
        "BU",
        "pursue.v.02",
        " SHO",
        "fad.n.01",
        "RONT",
        "EVERLASTING",
        "keep_up.v.04",
        "AS",
        "state_of_mind.n.01",
        "stone.n.02",
        "SSF",
        "HE",
        "ATTAIN",
        "ELY ",
        "EREA",
        "EN",
        " SU",
        "success.n.03",
        "_B",
        "AB",
        "state.n.02",
        "case.n.20",
        "identify.v.01",
        "TIN",
        "LL",
        "LI",
        "SHAL",
        "grammatical_category.n.01",
        " DIS",
        "make.v.33",
        "AL",
        " PR",
        "make.v.25",
        "SUR",
        "elect.v.01",
        "make.v.02",
        "ERT",
        " SH",
        "PON ",
        "RON",
        "create.v.05",
        "type.n.04",
        "able.s.03",
        "OLLO",
        " \u2013 ",
        "better.v.02",
        "return.v.06",
        "FT",
        "then.r.03",
        "AN",
        " SAV",
        "guarantee.v.02",
        "GION",
        "OM",
        "EATH",
        "GO_B",
        "death.n.02",
        "CCEE",
        "follow.v.07",
        "succeed.v.02",
        "N_TH",
        "force.v.08",
        "successful.a.01",
        "verily.r.01",
        "trace.v.01",
        " L",
        "cardinal_virtue.n.01",
        "turn.v.23",
        "TI",
        "ONE ",
        "O_BA",
        "LIG",
        "COV",
        " FOL",
        "shell.n.08",
        "turn.v.22",
        "constitute.v.01",
        "vascular_plant.n.01",
        "know.v.04",
        "COME",
        "keep_open.v.01",
        "PP",
        "rescue.v.01",
        " SUR",
        "re-create.v.01",
        "move.v.02",
        "prevail.v.03",
        "change_by_reversal.v.01",
        "prosperity.n.01",
        "think.v.01",
        "RO",
        "ITY",
        "ORE ",
        "URN",
        " VER",
        "ABUSE",
        "EVE",
        "EL",
        "till.v.01",
        "physical_entity.n.01",
        "change_of_state.n.01",
        "TH",
        "make.v.16",
        " CR",
        "AK",
        "result.v.01",
        "make.v.42",
        "REVERT",
        "unit_of_measurement.n.01",
        "K ",
        " THE",
        " VE",
        "force.v.06",
        "lawsuit.n.01",
        "circumstance.n.01",
        "lay_down.v.01",
        "appeal.v.02",
        "AR ",
        "indispose.v.03",
        " FO",
        "TY ",
        "ND ",
        "AP",
        "URE",
        "able.s.04",
        "religious_doctrine.n.01",
        "excrete.v.01",
        "wedge.v.02",
        "continue.v.03",
        "OT",
        "trait.n.01",
        "institution.n.01",
        "effect.v.01",
        "keep.v.03",
        " ATT",
        "WLED",
        "turn.v.07",
        "ELIG",
        "be.v.03",
        "IL",
        "WELL",
        "signal.n.01",
        "able.a.01",
        "check.v.01",
        "be.v.01",
        "D_O",
        "proceed.v.04",
        "TTA",
        "make.v.41",
        "SU",
        "relation.n.01",
        "TAIN",
        " WOU",
        " DEA",
        "TER ",
        "OSPE",
        "shape.v.03",
        "CU",
        "ALL ",
        " IND",
        "REE",
        "SC",
        " \u201c",
        "WOUL",
        "THEN",
        "ISCO",
        "force_out.n.01",
        "appear.v.05",
        "adjust.v.03",
        "COVE",
        "phenomenon.n.01",
        "distinguish.v.01",
        "UR",
        "case.n.10",
        "indeed.r.01",
        "reappear.v.01",
        "DEA",
        "AKE ",
        "FRO",
        "fortune.n.04",
        "tidy.v.01",
        "mean.v.03",
        "condition.n.03",
        "SSFU",
        " N",
        "person.n.01",
        " REL",
        " B",
        "change_shape.v.01",
        " PRO",
        "prevail.v.05",
        "unit.n.03",
        "GET ",
        "EV",
        "SHOULD",
        "organic_phenomenon.n.01",
        "gain.v.08",
        "FARE",
        "KNOW",
        "reach.v.01",
        "GI",
        "ERIL",
        " MAK",
        "happen.v.04",
        "KN",
        "know.v.05",
        "DE",
        "degree.n.01",
        "N_T",
        "S ",
        "BE",
        "eat.v.02",
        " CO",
        "_O",
        "OVE",
        "RELIGION",
        "LED",
        "turn.v.10",
        "create_from_raw_material.v.01",
        " BA",
        "disrespect.n.01",
        "HA",
        "ING ",
        "RCE",
        "generate.v.01",
        "_TO",
        "adopt.v.01",
        "TORE",
        "imitate.v.01",
        "temporary_state.n.01",
        "appoint.v.02",
        "pit.v.03",
        " CA",
        "theological_virtue.n.01",
        "BUS",
        "turn.v.19",
        "FA",
        "TT",
        "use.n.01",
        "render.v.05",
        "be.v.08",
        "OSP",
        "case.n.08",
        "retort.v.01",
        "OR",
        " DI",
        "arrant.s.01",
        "express.v.02",
        "carry_through.v.01",
        "SAVE",
        "make.v.47",
        "cooperation.n.01",
        "FTE",
        "SAVED",
        "manage.v.02",
        "act.v.01",
        "TUR",
        "container.n.01",
        "UL",
        "NLY ",
        " EV",
        "find_out.v.04",
        "make.v.35",
        "belief.n.01",
        "EED ",
        "US",
        "penetrate.v.01",
        "position.v.01",
        "RILY",
        "determine.v.01",
        "LT",
        "CULT",
        "TING",
        "score.v.01",
        "symbol.n.01",
        "_BA",
        "RE",
        " HAR",
        "GO_BACK",
        " FIN",
        "_U",
        " FI",
        "case.n.01",
        "make.v.03",
        " YE ",
        "prevail.v.02",
        "angiosperm.n.01",
        "get.v.01",
        "ME",
        " GET",
        "able.s.02",
        "ACK",
        " WH",
        "FUL",
        " ] ",
        "sheath.n.02",
        "SA",
        "make.v.49",
        "INDE",
        "TH ",
        "GE ",
        " SUC",
        "KE",
        "attribute.n.02",
        "SPE",
        "indefinite_quantity.n.01",
        "substance.n.01",
        "LL ",
        "ARE ",
        "VERILY",
        "change.n.03",
        "RES",
        "OLL",
        "REL",
        "recognize.v.02",
        "ELI",
        "follow.v.19",
        "YE ",
        "question.n.02",
        " \u201c ",
        "white_goods.n.02",
        "CAS",
        "calculate.v.01",
        "SUCCEED",
        "record.v.02",
        "IN_FRONT",
        "play.v.03",
        " BE",
        "faith.n.04",
        "EAR",
        "choose.v.01",
        "TAI",
        "CREED",
        "RC",
        "ABUS",
        "cognition.n.01",
        "STO",
        "APP",
        "rock.n.01",
        "VE",
        " CRE",
        "REV",
        "stone.n.09",
        "ESTO",
        "discrimination.n.02",
        "ITY ",
        "RN ",
        "ageless.s.01",
        " AP",
        "force.n.03",
        "originate.v.01",
        "HOU",
        "protective_covering.n.01",
        " WEL",
        "AND_",
        "material.n.01",
        "validity.n.02",
        " Y",
        "CR",
        "ASE ",
        "font.n.01",
        "good_fortune.n.01",
        "E_",
        "PRE",
        "AI",
        "sour.v.01",
        "content.n.05",
        "know.v.02",
        "fall_upon.v.01",
        " H",
        "prevail.v.04",
        "detect.v.01",
        "IN",
        "reach.v.02",
        "communicate.v.02",
        "M ",
        "ILY",
        " HA",
        "SCOV",
        "H ",
        "estimate.v.01",
        "push.v.01",
        "prove.v.01",
        "death.n.08",
        "RCE ",
        "Y ",
        "CEE",
        "handle.v.04",
        "_BAC",
        "change_state.v.01",
        "have.v.01",
        "UT",
        "process.n.06",
        "learn.v.02",
        " ]",
        "transfer.v.05",
        "WI",
        "TY",
        "failure.n.01",
        "make.v.43",
        "REVA",
        "AFT",
        "subject.n.06",
        "happening.n.01",
        "make.v.19",
        "SS",
        "ARE",
        "spy.v.03",
        " AND",
        "persevere.v.01",
        "D_TH",
        "RETURN",
        "HO",
        "reciprocate.v.01",
        "NDEE",
        "information.n.02",
        "therein.r.01",
        "appear.v.03",
        "stool.v.04",
        " HAP",
        "AT",
        "emotion.n.01",
        "save.v.06",
        "WILL",
        "MAKE",
        "AINL",
        " G",
        "NESS",
        "make.v.27",
        " K",
        "ME_U",
        "send.v.01",
        "termination.n.05",
        "ARM",
        "SP",
        "RIT",
        "character.n.08",
        "EA",
        "PER ",
        "ELY",
        "KNO",
        "HERE",
        "follow.v.03",
        "IND ",
        "force.n.02",
        " CU",
        "INLY",
        "AND",
        "LO",
        " DE",
        "natural_object.n.01",
        "pericarp.n.01",
        "act.n.02",
        "PE",
        "OWL",
        " \u2019",
        "TO",
        "definite_quantity.n.01",
        "EAF",
        "CEED",
        "follow.v.01",
        "come_back.v.01",
        "BACK",
        "know.v.10",
        "hit.v.09",
        "amount.v.01",
        "watch.v.02",
        "psychological_feature.n.01",
        "RLAS",
        "refer.v.04",
        "O ",
        "NDE",
        "AIL",
        "N_F",
        "FIN",
        "save.v.05",
        "T ",
        "turn.v.14",
        "ET ",
        "restore.v.05",
        "spermatophyte.n.01",
        "NG ",
        "_T",
        "case.n.11",
        "OUL",
        "stone.v.01",
        "_OU",
        "killing.n.02",
        "turn.v.26",
        "solid.n.01",
        "commitment.n.02",
        "stone.n.13",
        "act.v.02",
        "OW ",
        "make.v.38",
        "sleep_together.v.01",
        "make.v.14",
        "develop.v.10",
        "property.n.02",
        "\u2013 ",
        "EDG",
        "CO",
        "gem.n.02",
        "convey.v.03",
        "ORE",
        "PO",
        "seduce.v.01",
        "effect.n.05",
        "SPER",
        " S",
        "TURN",
        "USE ",
        "stone.n.12",
        "thrust.v.01",
        "CA",
        "exhaust.v.05",
        "religion.n.01",
        "PPI",
        "NOT ",
        "psychological_state.n.01",
        " GO_",
        "HAPP",
        "achiever.n.01",
        "ITH",
        "FOLL",
        " NO",
        "power.n.05",
        "GET",
        "IS",
        "VAIL",
        "APPE",
        "AT ",
        "put.v.01",
        "PREVAIL",
        "TER",
        "postdate.v.01",
        "make.v.34",
        "[",
        "cook.v.02",
        "DG",
        "putout.n.01",
        "ESS",
        "basic_cognitive_process.n.01",
        "indication.n.01",
        "IN_",
        "RT",
        "NE ",
        "damage.n.01",
        "FO",
        "WIL",
        "BLE ",
        "assemble.v.03",
        "perpetrate.v.01",
        "ABU",
        "LLOW",
        "PON",
        "make.v.24",
        "PROSPER",
        "commodity.n.01",
        "RN",
        "NEVER",
        "receptacle.n.01",
        "take.v.27",
        "turn.v.18",
        "whole.n.02",
        "aggression.n.03",
        " F",
        "refund.v.01",
        "turn.v.11",
        " \u201d ",
        "RM ",
        "out.n.01",
        " GO",
        "part.n.01",
        "SFUL",
        "FAIT",
        "know.v.09",
        "ahead.r.01",
        " MA",
        "DISC",
        "TO ",
        "death.n.05",
        "ND_O",
        "EDGE",
        "HAV",
        "ES",
        "see.v.05",
        "LY",
        "NOT",
        "OME",
        "RESTORE",
        "ERIT",
        " ABU",
        "direct.v.04",
        "RL",
        "attainment.n.01",
        "make.v.48",
        "E_U",
        "ORC",
        "know.v.03",
        "change_magnitude.v.01",
        "_THE",
        "surely.r.01",
        " FOR",
        "IT",
        "physical_condition.n.01",
        "IGIO",
        "VER",
        "IN_F",
        "ITH ",
        "ONT",
        "ER ",
        "come_to.v.04",
        "acknowledge.v.06",
        "NES",
        "HARM",
        "hurt.v.02",
        "accept.v.01",
        "PPE",
        "abuse.n.02",
        "control.v.01",
        "CK",
        "FUL ",
        "coldness.n.02",
        "unwrap.v.02",
        "SHOU",
        "ILL",
        "DGE",
        "E_UP",
        " NE",
        "MA",
        "reproduce.v.01",
        "record.v.01",
        "E ",
        "RI",
        "compel.v.01",
        "BAC",
        "HAL",
        "death.n.06",
        "AITH",
        "RETU",
        "AND_THEN",
        "NOW",
        " BAC",
        "linen.n.03",
        "measure.n.02",
        "EVER",
        "coerce.v.01",
        "good.n.02",
        "OS",
        "N_",
        "ATTA",
        " AB",
        "military_unit.n.01",
        "interact.v.01",
        "follow.v.23",
        "give.v.03",
        "VERI",
        "causal_agent.n.01",
        " [ ",
        "ELL",
        "mass_unit.n.01",
        "AR",
        "success.n.01",
        "FR",
        "LIGI",
        "taste.n.03",
        "induce.v.02",
        "SH",
        "hold.v.03",
        "decide.v.01",
        "HAPPINESS",
        "STONE",
        "render.v.04",
        "FRON",
        " PRE",
        "point.n.06",
        "restore.v.03",
        "WHEREAFTER",
        "arrange.v.01",
        "FIND_OUT",
        "make.v.44",
        "CUL",
        "ION",
        "STIN",
        "submit.v.01",
        "rock.n.02",
        "N_FR",
        "do.v.03",
        "pay.v.01",
        " LO",
        "GE",
        "morality.n.01",
        "determine.v.03",
        "IN ",
        "TON",
        "HEN ",
        "return.v.01",
        "become.v.03",
        "ND_",
        "OME_",
        "] ",
        "RET",
        " TUR",
        "follow.v.04",
        "framework.n.03",
        "ISC",
        "power.n.01",
        " LO ",
        "written_symbol.n.01",
        "IND_",
        "perceive.v.01",
        "WHER",
        " W",
        "form.v.02",
        "turn.v.13",
        "group_action.n.01",
        "ERTA",
        "AVED",
        "practice.v.04",
        "storm.v.02",
        "VER ",
        " REV",
        "legality.n.01",
        "faith.n.02",
        "CE ",
        "AKE",
        "NEV",
        "make.v.45",
        "avoirdupois_unit.n.01",
        "ASTI",
        "structure.n.01",
        "LD",
        "collection.n.01",
        "WHE",
        "then.r.01",
        "death.n.04",
        "save.v.02",
        "ERI",
        "CERTAINLY",
        "UREL",
        " A",
        "]",
        "do.v.04",
        "HAT ",
        "EED",
        "\u201c",
        "turn.v.01",
        " KN",
        "make.v.37",
        "EVAI",
        "arrive.v.01",
        "proceeding.n.01",
        "R ",
        "drygoods.n.01",
        "social_group.n.01",
        "_F",
        "NOW ",
        "living_thing.n.01",
        "ABLE",
        "understand.v.01",
        "ROS",
        "vogue.n.01",
        "INES",
        "MAK",
        "APPI",
        " SO",
        "pass.v.01",
        "then.r.02",
        "connect.v.01",
        "GO",
        "NEVE",
        "NOWL",
        "covering.n.01",
        " WI",
        "make.v.31",
        " V",
        "enter_upon.v.01",
        "go_back.v.01",
        "RTAI",
        "reason.v.03",
        "practice.n.01",
        "make.v.15",
        " CUL",
        "revert.v.01",
        "religion.n.02",
        "LA",
        "stick_to.v.02",
        "ER",
        "evaluate.v.02",
        "ABL",
        "E_TO",
        "save.v.04",
        "spare.v.01",
        "originate.v.02",
        "PROSPERITY",
        "FORC",
        "nonaccomplishment.n.01",
        "D_",
        "join.v.04",
        "SUCCESSFUL",
        "AFTE",
        "LAS",
        "recur.v.02",
        "LAST",
        " NEV",
        "stone.n.10",
        " COM",
        "obey.v.01",
        "thrive.v.02",
        "CES",
        "SS ",
        "quality.n.01",
        "problem.n.02",
        "PIN",
        "find.v.03",
        "AVE",
        " GE",
        "doctrine.n.01",
        "AIT",
        "event.n.02",
        "SHA",
        "LOW ",
        "EST",
        "FORCE",
        "turn.v.08",
        "FI",
        "gain.v.05",
        "RE ",
        "adult.n.01",
        "URN ",
        "stone.n.11",
        " CER",
        "[ ",
        "return.v.14",
        "spend.v.02",
        "DISCOVER",
        "move.v.03",
        "emotional_state.n.01",
        "return.v.07",
        "death.n.03",
        "ILY ",
        " IN_",
        " T",
        "\u201d",
        "appear.v.02",
        "HAP",
        "class.n.01",
        "RTA",
        "natural_phenomenon.n.01",
        "_UP",
        " FAR",
        " FAI",
        "UP",
        "FU",
        "LT ",
        "RITY",
        "ET",
        "argument.n.01",
        "aim.v.01",
        "change_of_integrity.n.01",
        "BL",
        "housing.n.02",
        "KE ",
        "VERT",
        "turn.v.06",
        "O_",
        "virtue.n.04",
        "D ",
        "proceed.v.02",
        "subject.n.01",
        "VE ",
        "OU",
        "FAR",
        "GO_",
        "case.n.06",
        "character.n.05",
        "evidence.n.02",
        "revert.v.02",
        " AT",
        "SUCC",
        "play_along.v.02",
        "win.v.01",
        "object.n.01",
        "unemotionality.n.02",
        "VA",
        " \u2019 ",
        "force.v.04",
        " E",
        "discolor.v.03",
        "save.v.09",
        " RE",
        "physical_phenomenon.n.01",
        "PPIN",
        "change_hands.v.01",
        "HAVE",
        "lawfulness.n.01",
        "act.v.03",
        "perform.v.01",
        "enter.v.01",
        "TU",
        "economic_condition.n.01",
        "NL",
        "IN_THAT",
        "ATH ",
        "COM",
        "make.v.18",
        "EVA",
        "end.n.06",
        " \u201d",
        " TH",
        "WH",
        "ATH",
        "PRO",
        "ESS ",
        "injury.n.01",
        "NE",
        " C",
        " NOT",
        "fare.v.02",
        "ND_T",
        " HAV",
        "OT ",
        "continue.v.10",
        "artifact.n.01",
        " CE",
        "TONE",
        "bring.v.01",
        "creed.n.01",
        "develop.v.13",
        "message.n.02",
        "transport.v.02",
        "OW",
        "deliver.v.08",
        "LY ",
        "experience.v.01",
        "PERI",
        "CERT",
        "AC",
        "maltreatment.n.01",
        "save.v.03",
        "take_after.v.02",
        "CK ",
        "SE ",
        "change.v.02",
        "_FRO",
        "stone.n.06",
        " IN",
        "mutate.v.01",
        "matter.n.03",
        "IN_T",
        "EN ",
        "analyze.v.01",
        "THE",
        "AVE ",
        "covering.n.02",
        " STO",
        "HAT",
        " EVE",
        "HEN",
        "building_material.n.01",
        "ALL",
        " RES",
        "BLE",
        "PER",
        "DIS",
        "head.v.01",
        "happen.v.01",
        "INDEED",
        " WO",
        "cult.n.03",
        "travel.v.01",
        "EAFT",
        "ERL",
        "CESS",
        "misuse.n.01",
        "DEAT",
        "think.v.03",
        "RELI",
        "abstraction.n.06",
        "have.v.17",
        "write.v.08",
        "CC",
        "fall.v.21",
        "\u2019 ",
        "communication.n.02",
        "HALL",
        "repair.v.01",
        "SHO",
        "group.n.01",
        "LD ",
        "work.v.05",
        "stone.n.07",
        "DEED",
        "IG",
        "comply.v.01",
        "accomplishment.n.01",
        "WE",
        "OV",
        "cause.v.01",
        "keep.v.01",
        "appear.v.06",
        "prevent.v.01",
        "activity.n.01",
        "stone.n.08",
        "EE",
        "_TO ",
        "remember.v.01",
        "follow.v.10",
        "come.v.05",
        "gestate.v.01",
        "damage.n.03",
        "case.n.09",
        "TE",
        "_OUT",
        "INL",
        "turn.v.20",
        "supporting_structure.n.01",
        "undergo.v.01",
        "render.v.07",
        "ETU",
        "RT ",
        "casing.n.03",
        "UCC",
        "SAV",
        "USE",
        "flex.v.05",
        "cult.n.01",
        "indeed.r.02",
        "EAT",
        "REA",
        "PEA",
        " SHA",
        "know.v.01",
        "VERL",
        "SURELY",
        "D_T",
        "HER",
        "UL ",
        " [",
        "OVER",
        "LO ",
        "perform.v.03",
        "intensity.n.02",
        "force.n.04",
        "CREE",
        "twist.v.10",
        "FOR",
        "process.n.02",
        "_UPO",
        "AST",
        "cult.n.04",
        "SO ",
        "eat.v.01",
        "ELL ",
        "CE",
        "DEATH",
        "ORCE",
        "make.v.08",
        "operate.v.03",
        "ON",
        "grow.v.02",
        "PREV",
        "senesce.v.01",
        "pull.v.01",
        "salvage.v.01",
        "\u201d ",
        "FAI",
        "CER",
        " ABL",
        "SF",
        "transmit.v.04",
        "increase.v.01",
        "PINE",
        "SE",
        "SHALL",
        " FA",
        "organization.n.01",
        "AF",
        "case.n.12",
        "fashion.n.03",
        "produce.v.02",
        "end.n.02",
        "feeling.n.01",
        "SFU",
        "_FR",
        "\u2013",
        "ED",
        "RIL",
        "prosperity.n.02",
        "BA",
        "OL",
        "UC",
        "WOU",
        "FOL",
        "AIL ",
        " P",
        "touch.v.01",
        " M",
        "NT",
        "hark_back.v.01",
        "BE ",
        "reach.v.07",
        "influence.n.01",
        "turn.v.04",
        "complete.v.01",
        "case.n.04",
        "STOR",
        "follow.v.06",
        "WEL",
        "TA",
        "OUT ",
        "O_B",
        "change.n.01",
        "create_by_mental_act.v.01",
        "ION ",
        "ST",
        "ND",
        "ARM ",
        "UCCE",
        "follow.v.08",
        "appear.v.04",
        "name.v.03",
        "WLE",
        "condition.n.01",
        "reserve.v.04",
        "ATT",
        " I",
        "happiness.n.02",
        "NLY",
        "ING",
        " ST",
        "case.n.05",
        "identify.v.05",
        "NG",
        "PROS",
        "ERE",
        "communicate.v.01",
        "turn.v.16",
        "stone.n.05",
        "organism.n.01",
        "force.n.08",
        "EAR ",
        "transform.v.02",
        "RM",
        "W ",
        "mistreatment.n.01",
        "COME_TO",
        "instrumentality.n.03",
        "ROSP",
        "LE ",
        "THA",
        "\u2019",
        "UPON",
        "INE",
        "construct.v.01",
        "L ",
        " WIL",
        "PEAR",
        "happiness.n.01",
        " BE ",
        "CCE",
        "make.v.30",
        "IND",
        " \u2013",
        "SURE",
        "injure.v.01",
        "PR",
        "ACK ",
        "due_process.n.01",
        "ULT",
        "ONE",
        "OULD",
        "ULT ",
        "refer.v.02",
        "ERLA",
        "_THA",
        "FOLLOW",
        "end.v.02",
        "case.n.18",
        "ERT ",
        "manipulate.v.02",
        "REAF",
        "look.v.02",
        "action.n.01",
        "transform.v.03",
        "FIND",
        "IGI",
        "WOULD",
        " TU",
        "WO",
        "CASE",
        " AN",
        "UT "
    ]
}