{
    "VERSE": "80:26",
    "ARABIC": "\u062b\u064f\u0645\u0651\u064e \u0634\u064e\u0642\u064e\u0642\u0652\u0646\u064e\u0627 \u0671\u0644\u0652\u0623\u064e\u0631\u0652\u0636\u064e \u0634\u064e\u0642\u0651\u064b\u0627",
    "ENGLISH": {
        "TRANSLATION_0": "then split the earth into furrows.",
        "TRANSLATION_1": "Then We cracked the earth open under pressure (of germination)\n",
        "TRANSLATION_2": "and cleaved the earth, cleaving it asunder;\n",
        "TRANSLATION_3": "and let the earth to break open\n",
        "TRANSLATION_4": "Then We split the earth properly.\n",
        "TRANSLATION_5": "And We split the earth in clefts.\n",
        "TRANSLATION_6": "Then We cleave the earth, cleaving (it) asunder,\n",
        "TRANSLATION_7": "then We split the earth in fissures\n",
        "TRANSLATION_8": "Then split the earth in clefts\n",
        "TRANSLATION_9": "and then We cleaved the earth asunder.\n",
        "TRANSLATION_10": "Thereafter We cleave the earth in clefts,\n",
        "TRANSLATION_11": "then We split the earth making fissures in it\n",
        "TRANSLATION_12": "And We split the earth in fragments,\n",
        "TRANSLATION_13": "And We split the earth in clefts,\n",
        "TRANSLATION_14": "and split the earth, splitting,\n",
        "TRANSLATION_15": "Then crack the soil open.\n",
        "TRANSLATION_16": "Then We broke open the earth, splitting [it with sprouts],\n",
        "TRANSLATION_17": "[80:26] then We split the earth into fissures, with vegetation,\n",
        "TRANSLATION_18": "(Then split the earth in clefts) through plants\n"
    },
    "CROSS_REFERENCE": {
        "QURAN": [
            "80:26",
            "51:48",
            "91:6",
            "84:3",
            "56:4",
            "99:2",
            "19:40",
            "89:21",
            "77:25",
            "23:79"
        ],
        "BIBLE": [
            "torah:leviticus:26:19",
            "torah:leviticus:22:22",
            "writings:ezra:9:14",
            "prophets:hosea:2:20",
            "prophets:isaiah:24:19",
            "prophets:hosea:10:11",
            "prophets:isaiah:42:3",
            "prophets:isaiah:14:7",
            "prophets:i%20kings:5:23",
            "torah:leviticus:11:33"
        ]
    },
    "FEATURES": [
        "LE",
        "total.v.01",
        "FTER",
        "seduce.v.01",
        "deaden.v.06",
        "force.n.01",
        " S",
        "G ",
        "inform.v.01",
        "EFT",
        "UN",
        "cling.v.01",
        "ROPE",
        "depression.n.08",
        "make.v.32",
        "exhaust.v.05",
        "leave.v.01",
        "psychological_state.n.01",
        "THER",
        "ED ",
        "crevice.n.01",
        "OIL",
        "FISSURES",
        "scat.v.01",
        "solve.v.01",
        "MAKI",
        "make.v.36",
        " ASU",
        "deprive.v.02",
        "IS",
        "apart.r.06",
        "candid.s.03",
        "shard.n.01",
        "curiosity.n.01",
        "put.v.01",
        "TER",
        "break.v.22",
        "make.v.34",
        "BREA",
        "[",
        "GERMINATION",
        "break.v.40",
        "cook.v.02",
        "break.v.56",
        "ESS",
        "earth.n.04",
        "basic_cognitive_process.n.01",
        "SPL",
        "crack.v.06",
        "ART",
        "RT",
        "SO",
        "N ",
        "ruin.v.02",
        "achieve.v.01",
        "regenerate.v.01",
        "RTH",
        "assemble.v.03",
        "EART",
        "perpetrate.v.01",
        "FURR",
        "make.v.24",
        "make.v.01",
        "crack.v.10",
        "MI",
        "ON ",
        "UTS",
        "order.v.05",
        "take.v.27",
        "break.v.59",
        "urgency.n.01",
        "whole.n.02",
        "transgress.v.01",
        "germination.n.01",
        "location.n.01",
        "IL ",
        "dampen.v.07",
        "pressure.n.05",
        "succeed.v.01",
        " F",
        "OUT",
        "_OP",
        "UNDE",
        "part.n.01",
        "hit.v.01",
        "disrespect.v.01",
        "accept.v.03",
        " MA",
        "ROK",
        "land.n.02",
        "KED",
        "CLEAVE",
        "entity.n.01",
        "FRAGMENTS",
        "open.a.02",
        "invalidate.v.01",
        "MEN",
        "AGME",
        "ES",
        "see.v.05",
        "RTH ",
        "LY",
        "refrain.v.01",
        "press.n.09",
        "persuade.v.02",
        "direct.v.04",
        "SSUR",
        "RL",
        "KI",
        "make.v.48",
        "GERM",
        "develop.v.14",
        "AV",
        "change_magnitude.v.01",
        "do.v.08",
        "NAT",
        "change.v.06",
        "IT",
        "misfortune.n.02",
        "ROW",
        "ER ",
        "tell.v.02",
        "crack.v.04",
        "draw.v.04",
        " OP",
        " O",
        "IO",
        "make.v.46",
        "hurt.v.02",
        "open.a.05",
        "VED ",
        "event.n.01",
        "control.v.01",
        "change.v.01",
        "CK",
        "asunder.s.01",
        "SOIL",
        "shoot.v.08",
        "unwrap.v.02",
        "MA",
        "VED",
        "ASUNDER",
        "E ",
        "interest.n.01",
        "break.v.30",
        "break.v.35",
        "break.v.26",
        "KIN",
        "crack.v.12",
        "AS",
        "clear.s.03",
        "decrease.v.01",
        "RRO",
        "HE",
        "CLEA",
        "EREA",
        "EAVI",
        "give.v.03",
        "interact.v.01",
        " [ ",
        "EN",
        "ROP",
        "SPLI",
        "thing.n.12",
        "perception.n.03",
        "AR",
        "FR",
        "state.n.02",
        "tell.v.03",
        "NTS ",
        "geographical_area.n.01",
        "break.v.39",
        "induce.v.02",
        "break.v.46",
        "hold.v.03",
        "TIN",
        "LI",
        "FUR",
        " PRE",
        "make.v.33",
        " PR",
        "become.v.01",
        "GER",
        "come_forth.v.02",
        "arrange.v.01",
        "make.v.25",
        "UND",
        "make.v.44",
        "SUR",
        "ION",
        "make.v.02",
        "SUN",
        "ARTH",
        "break.v.10",
        "create.v.05",
        "GE",
        " EAR",
        "replace.v.01",
        "pressure.n.01",
        "HEN ",
        "vegetable.n.01",
        "space.n.02",
        "become.v.03",
        "URES",
        "body_part.n.01",
        "] ",
        "break.v.27",
        "FT",
        "ASU",
        "intensify.v.03",
        "then.r.03",
        "break.v.50",
        "separate.v.08",
        "separate.v.07",
        "power.n.01",
        " OPE",
        "guarantee.v.02",
        "CRACKED",
        "PEN",
        "K_",
        "propel.v.01",
        "SPROUTS",
        "trespass.v.01",
        "crack.v.01",
        "break.v.25",
        "break.v.44",
        "_OPE",
        "AG",
        "form.v.02",
        "AVED",
        "break.v.16",
        "AK_O",
        " L",
        "necessity.n.01",
        "TI",
        " SPL",
        "groove.n.03",
        "ROWS",
        "FTS ",
        "weaken.v.01",
        "make.v.45",
        "MAKING",
        "plant_part.n.01",
        " BRO",
        "CLEAVED",
        "constitute.v.01",
        "break.v.51",
        "OWS",
        "PROP",
        "express_emotion.v.01",
        "then.r.01",
        "OWS ",
        "re-create.v.01",
        "move.v.02",
        "think.v.01",
        "RO",
        "lease.v.03",
        " A",
        "AKIN",
        "]",
        "DER ",
        "physical_entity.n.01",
        "territory.n.03",
        "TH",
        "make.v.16",
        "AK",
        "piece.n.06",
        "soil.n.02",
        " CR",
        "earth.n.05",
        "make.v.42",
        "make.v.37",
        "break_in.v.06",
        "K ",
        "growth.n.01",
        " THE",
        "concern.n.01",
        "amorphous_shape.n.01",
        "R ",
        "cleave.v.02",
        "propulsion.n.02",
        "REAK",
        "lay_down.v.01",
        "let.v.02",
        "open.s.04",
        "PEN ",
        "understand.v.01",
        " SP",
        "indispose.v.03",
        "MAK",
        "RMIN",
        " SO",
        "thwart.v.01",
        "K_OP",
        "earth.n.02",
        "FIS",
        "pass.v.01",
        "then.r.02",
        "break.v.08",
        "worldly_concern.n.01",
        "OI",
        "snap.v.06",
        "URE",
        "BRE",
        "make.v.31",
        "snap.v.03",
        "RACK",
        "fail.v.04",
        "excrete.v.01",
        "reason.v.03",
        "DER",
        "OP",
        "earth.n.01",
        "pause.v.02",
        "impoverish.v.01",
        "make.v.15",
        "ATI",
        "break_open.v.01",
        "OK",
        "wrinkle.n.01",
        "discontinue.v.01",
        "BR",
        "open.a.01",
        "VING",
        "URRO",
        "ER",
        "evaluate.v.02",
        "plant_organ.n.01",
        "open.s.17",
        "keep.v.03",
        "BROK",
        "AFTE",
        "IL",
        "SSU",
        "RESS",
        "be.v.01",
        "relate.v.05",
        "get_the_better_of.v.01",
        "ground.n.09",
        "SU",
        "make.v.41",
        "cognitive_state.n.01",
        "relation.n.01",
        "quality.n.01",
        "sprout.n.01",
        "deny.v.04",
        "capable.s.02",
        "divide.v.01",
        "fissure.n.03",
        "land.n.04",
        " GE",
        "AVE",
        "TER ",
        "AVIN",
        "FI",
        " FUR",
        "gain.v.05",
        "RE ",
        "URR",
        "ERMI",
        "[ ",
        "flee.v.01",
        "WS ",
        "move.v.03",
        "THEN",
        "loose.s.09",
        "NDER",
        "LIT ",
        "damage.v.01",
        " AS",
        "LIT",
        " T",
        "RAC",
        "UR",
        "phenomenon.n.01",
        "ASUN",
        " BRE",
        "appear.v.02",
        "piece.n.01",
        "PL",
        "break_through.v.01",
        "natural_phenomenon.n.01",
        "withhold.v.01",
        "fortune.n.04",
        "INAT",
        "tear.v.02",
        "tidy.v.01",
        "UTS ",
        "FU",
        " GER",
        "PRES",
        "break.v.24",
        "condition.n.03",
        "ET",
        "SPRO",
        "OPEN",
        " B",
        "sound.v.02",
        "indentation.n.01",
        " PRO",
        "ERLY",
        "KE ",
        "TIO",
        "break.v.55",
        "by_rights.r.01",
        "ISS",
        "D ",
        "GM",
        " FIS",
        "proceed.v.02",
        "suffer.v.02",
        "OKE",
        "gain.v.08",
        "open.s.12",
        "produce.n.01",
        "OU",
        "VE ",
        " EA",
        "MENT",
        "reach.v.01",
        "gas_pressure.n.01",
        " FRA",
        "germination.n.02",
        " MAK",
        " SPR",
        "DE",
        "EAK",
        "S ",
        "bankrupt.v.01",
        "_O",
        "break.v.58",
        "break.v.18",
        "delegate.v.02",
        "break.v.34",
        "object.n.01",
        "organic_process.n.01",
        "EAV",
        "create_from_raw_material.v.01",
        "open.s.07",
        "WS",
        " E",
        "physical_phenomenon.n.01",
        "sprout.n.02",
        "act.v.03",
        "disconnect.v.02",
        "ING ",
        "perform.v.01",
        "enter.v.01",
        "BREAK_OPEN",
        "generate.v.01",
        "CKED",
        "INA",
        "IT ",
        "break.v.03",
        "OPER",
        "BRO",
        "make.v.18",
        "break.v.28",
        "appoint.v.02",
        " TH",
        "PRO",
        "TT",
        "hit.v.03",
        " C",
        "crack_up.v.01",
        "fragment.n.01",
        "dirt.n.02",
        "shape.n.02",
        "separate.v.02",
        "LET",
        "break_dance.v.01",
        "break.v.45",
        "break.v.53",
        "break.v.09",
        "concave_shape.n.01",
        "artifact.n.01",
        "CLEF",
        "ISSU",
        "creation.n.02",
        "push.n.01",
        "origin.n.03",
        "furrow.n.01",
        "develop.v.13",
        "ROKE",
        "OW",
        "FTS",
        "make.v.47",
        "separate.v.09",
        "LET ",
        "leave.v.04",
        "SUND",
        "FTE",
        "need.n.01",
        "LY ",
        "decay.v.02",
        "assailable.s.01",
        "AC",
        "manage.v.02",
        "act.v.01",
        "ROUT",
        "crack.v.13",
        "break.v.23",
        "GME",
        "CK ",
        "change.v.02",
        "atmospheric_pressure.n.01",
        "RLY ",
        "FRA",
        "matter.n.03",
        "PROPERLY",
        "make.v.35",
        "food.n.02",
        "EN ",
        "break.v.05",
        "penetrate.v.01",
        "THEREAFTER",
        "AVE ",
        "THE",
        "part.n.03",
        "HEN",
        "TING",
        "score.v.01",
        "fracture.v.06",
        "violate.v.01",
        "RE",
        "CLEFTS",
        "PER",
        "cleft.n.01",
        " FI",
        "TS ",
        "make.v.03",
        "AK_",
        "pressure.n.06",
        "SPLITTING",
        "connection.n.03",
        "ITT",
        "head.v.01",
        "burst.v.01",
        "cause_to_be_perceived.v.01",
        "get.v.01",
        "happen.v.01",
        "ME",
        "RES ",
        "EAFT",
        "travel.v.01",
        "ERL",
        "ACK",
        "think.v.03",
        "change.v.03",
        " ] ",
        "abstraction.n.06",
        "PLIT",
        "CKE",
        "make.v.49",
        "TH ",
        "have.v.17",
        "KE",
        " LET",
        "GMEN",
        "diphthongize.v.01",
        "CRAC",
        "declare.v.04",
        "attribute.n.02",
        "EAK_",
        "break.v.38",
        "substance.n.01",
        "get.v.03",
        "CRA",
        "properly.r.01",
        "RES",
        "EARTH",
        "ES ",
        "break.v.52",
        "BROKE",
        "cause.v.01",
        "AGM",
        "prevent.v.01",
        "erupt.v.02",
        "part.n.02",
        "beat.v.01",
        "break.v.49",
        "calculate.v.01",
        "domesticate.v.02",
        "adversity.n.01",
        "CL",
        "break.v.02",
        "region.n.03",
        "EAR",
        "disperse.v.04",
        "cleave.v.01",
        " SOI",
        "TE",
        "ditch.n.01",
        "undergo.v.01",
        "NTS",
        "cognition.n.01",
        " CL",
        "imperativeness.n.01",
        "AKI",
        "destroy.v.02",
        "break.v.41",
        "VE",
        "NA",
        "REA",
        "touch.v.05",
        "RROW",
        "LEA",
        "permit.v.01",
        "OPE",
        "TTIN",
        "OUTS",
        "originate.v.01",
        "HER",
        " [",
        "TS",
        "material.n.01",
        "PRESSURE",
        "CR",
        "RLY",
        "process.n.02",
        "beginning.n.01",
        "RMI",
        "receptive.a.02",
        "KING",
        " CLE",
        "PRE",
        "make.v.08",
        "CLEAVING",
        "PROU",
        "LITT",
        "ON",
        "RAGM",
        "open.s.10",
        "dance.v.02",
        "thereafter.r.01",
        "IN",
        "communicate.v.02",
        "fragment.n.03",
        "let.v.05",
        "TTI",
        "open.v.01",
        "crack.v.11",
        "H ",
        "estimate.v.01",
        "FISS",
        "increase.v.01",
        "Y ",
        "change_state.v.01",
        "AF",
        "have.v.01",
        "UT",
        "process.n.06",
        "produce.v.02",
        "CRACK",
        " ]",
        "transfer.v.05",
        "open.s.21",
        "break.v.20",
        "make.v.43",
        "AFT",
        " LE",
        "ED",
        "RAG",
        "AVI",
        "interrupt.v.01",
        "happening.n.01",
        "switch.v.03",
        "SS",
        "make.v.19",
        "SPR",
        "RR",
        "element.n.05",
        " P",
        "touch.v.01",
        " M",
        "open.a.11",
        "NT",
        "reach.v.07",
        "greens.n.01",
        "influence.n.01",
        "exposed.s.01",
        "excavation.n.03",
        "ACKE",
        "VIN",
        "stool.v.04",
        "separate.v.05",
        "ITTI",
        "AT",
        "somesthesia.n.01",
        "demote.v.01",
        "create_by_mental_act.v.01",
        "rending.s.01",
        "trench.n.03",
        "ION ",
        " FU",
        "pressure.n.02",
        "ND",
        "ENTS",
        " G",
        "break.v.42",
        "SOI",
        "make.v.27",
        "LEF",
        "name.v.03",
        "condition.n.01",
        "ENT",
        "crack.n.01",
        "EFTS",
        "SP",
        "surpass.v.02",
        " BR",
        "break.v.07",
        "decompose.v.01",
        "K_O",
        "ING",
        "EA",
        "FURROWS",
        "opening.n.01",
        "NG",
        "open.s.06",
        "HERE",
        "PLI",
        "ERE",
        "cancel.v.03",
        "URE ",
        "SPLIT",
        "react.v.01",
        "RM",
        "KED ",
        "natural_object.n.01",
        "MIN",
        "break.v.48",
        "OIL ",
        " FR",
        "break.v.29",
        "open.s.14",
        "FRAG",
        "act.n.02",
        "PE",
        "open.s.13",
        "instrumentality.n.03",
        "EF",
        "EAF",
        "ATIO",
        "crack.v.02",
        "PERL",
        "ERM",
        "L ",
        "construct.v.01",
        "EAVE",
        "LEFT",
        "escape.v.01",
        "amount.v.01",
        "OKE ",
        "CLE",
        "solid.n.03",
        "make.v.30",
        "let.v.01",
        "psychological_feature.n.01",
        "break_in.v.01",
        "SURE",
        "break.v.04",
        "distress.n.02",
        "better.v.01",
        "experience.v.03",
        "NDE",
        "injure.v.01",
        "collapse.v.01",
        "T ",
        "LEAV",
        "overt.a.01",
        "PR",
        "ET ",
        "break.v.43",
        "ACK ",
        "detach.v.01",
        "MINA",
        "NG ",
        "interrupt.v.04",
        "end.v.02",
        "ESSU",
        "ROU",
        " CRA",
        "NATI",
        "dirtiness.n.01",
        "crack.v.08",
        "REAF",
        "look.v.02",
        "solid.n.01",
        "sanitary_condition.n.01",
        "VI",
        "RA",
        "act.v.02",
        "end.v.01",
        "make.v.38",
        "change_integrity.v.01",
        "make.v.14",
        "break.v.19",
        "TION"
    ]
}