{
    "VERSE": "36:25",
    "ARABIC": "\u0625\u0650\u0646\u0651\u0650\u0649\u0653 \u0621\u064e\u0627\u0645\u064e\u0646\u062a\u064f \u0628\u0650\u0631\u064e\u0628\u0651\u0650\u0643\u064f\u0645\u0652 \u0641\u064e\u0671\u0633\u0652\u0645\u064e\u0639\u064f\u0648\u0646\u0650",
    "ENGLISH": {
        "TRANSLATION_0": "I have iman in your Lord so listen to me!'",
        "TRANSLATION_1": "I believe in your Lord, so listen to me.\"\n",
        "TRANSLATION_2": "I believe in your Lord; so listen to me.\u201d\n",
        "TRANSLATION_3": "Messengers, listen to me. I believe in your Lord.\"\n",
        "TRANSLATION_4": "\u201cIndeed I have believed in your Lord, so heed me.\u201d\n",
        "TRANSLATION_5": "Verily, I have believed in your Lord, so listen to me!\"\n",
        "TRANSLATION_6": "Surely I believe in your Lord, therefore hear me.\n",
        "TRANSLATION_7": "Behold, I believe in your Lord; therefore hear me!'\n",
        "TRANSLATION_8": "Lo! I have believed in your Lord, so hear me!\n",
        "TRANSLATION_9": "Indeed, I have believed in your Lord, so listen to me.\"\n",
        "TRANSLATION_10": "Verily I believe now in your Lord; so hearken Unto me.\"\n",
        "TRANSLATION_11": "Indeed I have faith in your Lord, so listen to me.\u2019\n",
        "TRANSLATION_12": "For me, I have faith in the Lord of you (all): listen, then, to me!\"\n",
        "TRANSLATION_13": "Verily! I have believed in your Lord, so listen to me!\"\n",
        "TRANSLATION_14": "I believe in your Lord, so hear me'\n",
        "TRANSLATION_15": "I have believed in your Lord, so listen to me.\u201d\n",
        "TRANSLATION_16": "Indeed, I have believed in your Lord, so listen to me.\"\n",
        "TRANSLATION_17": "[36:25] Lo! I believe in your Lord. So listen to me!\u2019, in other words, hear what I have to say; but they stoned him and he died.\n",
        "TRANSLATION_18": "498 (Lo! I have believed in your Lord, so hear me) so obey me regarding faith; it is also said that he said this to the apostles: 'I believe in your Lord, so be witnesses that I am the slave of Allah'. He was then taken away and killed, crucified and trodden upon until his entrails burst forth from his rectum.\n"
    },
    "CROSS_REFERENCE": {
        "QURAN": [
            "36:25",
            "44:20",
            "54:10",
            "37:31",
            "23:107",
            "26:12",
            "23:26",
            "7:125",
            "23:39",
            "99:5"
        ],
        "BIBLE": [
            "prophets:jeremiah:11:11",
            "torah:exodus:4:1",
            "prophets:ezekiel:13:8",
            "prophets:ii%20kings:17:14",
            "torah:exodus:6:12",
            "prophets:jeremiah:25:8",
            "prophets:ezekiel:34:20",
            "prophets:i%20samuel:12:13",
            "writings:ii%20chronicles:28:11",
            "torah:numbers:32:23"
        ]
    },
    "FEATURES": [
        "NO",
        "virtue.n.04",
        "EV",
        "D ",
        "overlord.n.01",
        "hear.v.01",
        " IMA",
        "EVED",
        "ORE",
        "VE ",
        "LIE",
        "KEN",
        "HEE",
        "ERIL",
        " S",
        "DE",
        "SENG",
        "BE",
        "S ",
        "HEED",
        "object.n.01",
        "religion.n.01",
        "HEA",
        "EH",
        "probe.v.01",
        "godhead.n.01",
        " SO ",
        "THER",
        " \u2019 ",
        "ED ",
        "BEH",
        "HA",
        "HAVE",
        "ITH",
        " NO",
        "IEVE",
        "EHOL",
        " \u201d",
        "ESSE",
        "IS",
        " TH",
        "theological_virtue.n.01",
        "FA",
        "NGER",
        "DEE",
        " HAV",
        "male_aristocrat.n.01",
        "aristocrat.n.01",
        "RK",
        "ESS",
        "\u201c ",
        "OR",
        "LIST",
        "FO",
        "SO",
        "N ",
        "ENGE",
        "OW",
        "NGE",
        " IM",
        "cooperation.n.01",
        "LY ",
        "OLD ",
        "change.v.02",
        "FORE",
        " IN",
        "belief.n.01",
        "MAN",
        "whole.n.02",
        "EED ",
        "EN ",
        "RS",
        "analyze.v.01",
        " F",
        "AVE ",
        "THE",
        " \u201d ",
        "RILY",
        "ELIE",
        "FAIT",
        "HEN",
        " NOW",
        "RE",
        "pick_up.v.09",
        "ERS ",
        "BELI",
        "entity.n.01",
        "_IN ",
        "HAV",
        "ES",
        "RELY",
        "THEREFORE",
        " LOR",
        "LY",
        "INDEED",
        "ME",
        "AV",
        "LIEV",
        "think.v.03",
        "ISTE",
        "surely.r.01",
        "abstraction.n.06",
        "IT",
        "VER",
        "ITH ",
        "BEHO",
        "INDE",
        "TH ",
        "LIS",
        "BELIEVE_IN",
        "KE",
        "EFO",
        "\u2019 ",
        "attribute.n.02",
        "accept.v.01",
        "VED ",
        "event.n.01",
        "FAITH",
        "VERILY",
        "VE_I",
        "group.n.01",
        "LD ",
        "MA",
        "DEED",
        "REL",
        "VED",
        "ELI",
        "E ",
        "RI",
        "believe.v.03",
        "AITH",
        " \u201c ",
        "RD",
        "NOW",
        "ruler.n.01",
        "LISTEN",
        "EE",
        "good.n.02",
        " ME",
        " BE",
        "faith.n.04",
        "HE",
        "EAR",
        "hark.v.01",
        "ELY ",
        "STE",
        "listen.v.02",
        "VERI",
        "causal_agent.n.01",
        "EN",
        " LIS",
        "TE",
        " HEA",
        "AR",
        " SU",
        "EARK",
        "cognition.n.01",
        " MES",
        "VE_",
        "lord.n.03",
        "believe_in.v.01",
        "LI",
        "VE",
        "indeed.r.02",
        "GER",
        "OLD",
        "SUR",
        "ARK",
        "SURELY",
        "hear.v.04",
        "HER",
        "GE",
        " LO",
        "morality.n.01",
        "IN ",
        "LO ",
        "REF",
        "LOR",
        "BELIEVED",
        "messenger.n.01",
        "HEN ",
        "RKE",
        "FOR",
        " HE",
        "SO ",
        "E_",
        "E_I",
        "AI",
        "HOLD",
        "AN",
        "content.n.05",
        " LO ",
        " H",
        "MESSENGERS",
        "IN",
        "FAI",
        "perceive.v.01",
        "\u201d ",
        "ILY",
        "verily.r.01",
        "group_action.n.01",
        " HA",
        "investigate.v.01",
        "STEN",
        " L",
        "cardinal_virtue.n.01",
        "H ",
        "faith.n.02",
        "MESS",
        " LI",
        "SE",
        "Y ",
        "LD",
        "RKEN",
        " FA",
        "leader.n.01",
        "organization.n.01",
        "learn.v.02",
        "believe.v.01",
        "IST",
        "BEHOLD",
        "listen.v.01",
        " SUR",
        "ERI",
        "think.v.01",
        "UREL",
        "ED",
        "RIL",
        "ORE ",
        " VER",
        "EVE",
        "EL",
        "physical_entity.n.01",
        "OL",
        "_IN",
        "TH",
        "SS",
        "MES",
        "EFOR",
        " M",
        "EED",
        "\u201c",
        "HO",
        "BELIEVE",
        "NDEE",
        "expect.v.01",
        " THE",
        "believe.v.05",
        " VE",
        "R ",
        "social_group.n.01",
        "NOW ",
        "SSEN",
        "living_thing.n.01",
        "ST",
        "EHO",
        "IEV",
        "ND",
        "AR ",
        "heed.v.01",
        "LORD",
        " SO",
        "see.v.01",
        "credit.v.04",
        "behold.v.01",
        " BEL",
        "IMAN",
        "URE",
        " V",
        "believe.v.04",
        "E_IN",
        " I",
        "IM",
        "HEARKEN",
        "EA",
        "EREF",
        "concentrate.v.02",
        "ELY",
        "NG",
        "HERE",
        "ORD ",
        "ERE",
        "trust.v.01",
        "TEN",
        "organism.n.01",
        "religion.n.02",
        "EVE_",
        "LO",
        "ER",
        "evaluate.v.02",
        "institution.n.01",
        "EAR ",
        "ARKE",
        "W ",
        "IL",
        "act.n.02",
        "EVE ",
        " \u2019",
        "EF",
        "obey.v.01",
        "SU",
        "\u2019",
        "SEN",
        " BEH",
        "quality.n.01",
        "ORD",
        "REFO",
        "ENG",
        "TEN ",
        "AVE",
        "AIT",
        "traveler.n.01",
        " HEE",
        "RE ",
        "IND",
        "psychological_feature.n.01",
        " IND",
        "O ",
        "SURE",
        "IMA",
        "NDE",
        " \u201c",
        "_I",
        "THEN",
        "HEAR",
        "HOL",
        "IE",
        "SSE",
        "adjust.v.03",
        "ERS",
        " T",
        "UR",
        "\u201d",
        "ILY ",
        "GERS",
        "indeed.r.01",
        "RS ",
        "MAN ",
        " FAI",
        "KEN ",
        "commitment.n.02",
        "person.n.01",
        " N",
        "hear.v.03",
        " B",
        "OW ",
        "BEL",
        "RD ",
        "AN "
    ]
}