{
    "VERSE": "10:7",
    "ARABIC": "\u0625\u0650\u0646\u0651\u064e \u0671\u0644\u0651\u064e\u0630\u0650\u064a\u0646\u064e \u0644\u064e\u0627 \u064a\u064e\u0631\u0652\u062c\u064f\u0648\u0646\u064e \u0644\u0650\u0642\u064e\u0627\u0653\u0621\u064e\u0646\u064e\u0627 \u0648\u064e\u0631\u064e\u0636\u064f\u0648\u0627\u06df \u0628\u0650\u0671\u0644\u0652\u062d\u064e\u064a\u064e\u0648\u0670\u0629\u0650 \u0671\u0644\u062f\u0651\u064f\u0646\u0652\u064a\u064e\u0627 \u0648\u064e\u0671\u0637\u0652\u0645\u064e\u0623\u064e\u0646\u0651\u064f\u0648\u0627\u06df \u0628\u0650\u0647\u064e\u0627 \u0648\u064e\u0671\u0644\u0651\u064e\u0630\u0650\u064a\u0646\u064e \u0647\u064f\u0645\u0652 \u0639\u064e\u0646\u0652 \u0621\u064e\u0627\u064a\u064e\u0670\u062a\u0650\u0646\u064e\u0627 \u063a\u064e\u0670\u0641\u0650\u0644\u064f\u0648\u0646\u064e",
    "ENGLISH": {
        "TRANSLATION_0": "As for those who do not expect to meet Us and are content with the life of the dunya and at rest in it, and those who are heedless of Our Signs,",
        "TRANSLATION_1": "As for those who do not hope to meet Us (after death), and are content with the life of this world, who are oblivious of Our signs,\n",
        "TRANSLATION_2": "Surely those who do not expect to meet Us, who are gratified with the life of the world and content with it, and are heedless of Our signs,\n",
        "TRANSLATION_3": "Those who do not have hope of receiving Our mercy in the life hereafter who are pleased and satisfied with the worldly life and who pay no attention to Our revelations\n",
        "TRANSLATION_4": "Indeed those who do not expect to meet Us and have preferred the worldly life and are content with it, and those who neglect Our signs, \u2013\n",
        "TRANSLATION_5": "Verily, those who hope not for their meeting with Us, but are pleased and satisfied with the life of the present world, and those who are heedless of Our Ayat,\n",
        "TRANSLATION_6": "Surely those who do not hope in Our meeting and are pleased with this world's life and are content with it, and those who are heedless of Our communications:\n",
        "TRANSLATION_7": "Surely those who look not to encounter Us and are well-pleased with the present life and are at rest in it, and those who are heedless of Our signs,\n",
        "TRANSLATION_8": "Lo! those who expect not the meeting with Us but desire the life of the world and feel secure therein, and those who are neglectful of Our revelations,\n",
        "TRANSLATION_9": "Those who entertain no hope of meeting Us, being pleased and contented with the life of this world, and those who give no heed to Our signs,\n",
        "TRANSLATION_10": "Verily those who hope not for meeting with us, and, well- pleased with the life of the world, and are satisfied therewith, and those who are neglectful of our signs.\n",
        "TRANSLATION_11": "Indeed those who do not expect to encounter Us and who are pleased with the life of this world and satisfied with it, and those who are oblivious of Our signs\n",
        "TRANSLATION_12": "Those who rest not their hope on their meeting with Us, but are pleased and satisfied with the life of the present, and those who heed not Our Signs,-\n",
        "TRANSLATION_13": "Verily, those who hope not for their meeting with Us, but are pleased and satisfied with the life of the present world, and those who are heedless of Our Ayat (proofs, evidences, verses, lessons, signs, revelations, etc.),\n",
        "TRANSLATION_14": "Those who do not expect to meet Us, and are wellpleased with this life and are satisfied with it, and those who are inattentive to Our signs,\n",
        "TRANSLATION_15": "Those who do not hope to meet Us, and are content with the worldly life, and are at ease in it, and those who pay no heed to Our signs.\n",
        "TRANSLATION_16": "Indeed, those who do not expect the meeting with Us and are satisfied with the life of this world and feel secure therein and those who are heedless of Our signs\n",
        "TRANSLATION_17": "[10:7] Truly those who do not expect to encounter Us, through resurrection, and are content with the life of this world, instead of [the life] the Hereafter, since they reject [the truth of] it, and feel reassured, feel secure, in it, and those who are heedless of Our signs, [of] the proofs of Our Oneness, neglecting to ponder them,\n",
        "TRANSLATION_18": "(Lo! those who expect not) those who fear not (the meeting with Us) through resurrection after death; it is also said that this means: those who do not believe in resurrection after death (but desire the life of the world) but choose instead what is in the life of this world over the Hereafter (and feel secure therein) and are pleased with this life, (and those who are neglectful) deniers (of Our revelations) Muhammad (pbuh) and the Qur'an,\n"
    },
    "CROSS_REFERENCE": {
        "QURAN": [
            "10:7",
            "23:37",
            "6:29",
            "53:29",
            "79:38",
            "30:7",
            "2:86",
            "20:72",
            "40:51",
            "14:27"
        ],
        "BIBLE": [
            "writings:proverbs:13:12",
            "torah:deuteronomy:30:19",
            "torah:genesis:19:19",
            "torah:numbers:17:3",
            "writings:proverbs:19:23",
            "prophets:jonah:1:14",
            "torah:exodus:31:17",
            "writings:psalms:17:14",
            "prophets:habakkuk:2:5",
            "prophets:ii%20samuel:15:21"
        ],
        "KABBALAH": [
            "Sefer%20Yetzirah:6:1",
            "Sefer%20Yetzirah:4:12",
            "Sefer%20Yetzirah:4:1",
            "Sefer%20Yetzirah:2:5",
            "Sefer%20Yetzirah:4:3",
            "Sefer%20Yetzirah:4:4",
            "Sefer%20Yetzirah:6:4",
            "Sefer%20Yetzirah:1:13",
            "Sefer%20Yetzirah:5:1",
            "Sefer%20Yetzirah:5:2"
        ]
    }
}